; This file has been disassembled by the Lua 5 disassembler by Mike Lankamp
;
; Original file: 2dlayerdir_f.lub
; File format:   Lua 5.0
; Disassembled:  Sun Feb 12 00:35:35 2012
;

; Name:            @Lua Files Source\Lua Files\SprEditInfo\2DLayerDir_F.lua
; Defined at line: 0
; #Upvalues:       0
; #Parameters:     0
; Is_vararg:       0
; Max Stack Size:  3
;
; No locals information
; No upvalues

  1 [  1]: LOADK     R0 K1        ; R0 := 0
  2 [  1]: SETGLOBAL R0 K0        ; SEX_FEMALE := R0
  3 [  2]: LOADK     R0 K3        ; R0 := 1
  4 [  2]: SETGLOBAL R0 K2        ; SEX_MALE := R0
  5 [  4]: LOADK     R0 K1        ; R0 := 0
  6 [  4]: SETGLOBAL R0 K4        ; LAYER_BIG := R0
  7 [  5]: LOADK     R0 K3        ; R0 := 1
  8 [  5]: SETGLOBAL R0 K5        ; LAYER_SMALL := R0
  9 [  7]: NEWTABLE  R0 0 0       ; R0 := {}
 10 [  9]: GETGLOBAL R1 K7        ; R1 := SPRITE_ROBE_IDs
 11 [  9]: GETTABLE  R1 R1 K8     ; R1 := R1["ROBE_WINGS"]
 12 [  9]: GETGLOBAL R2 K4        ; R2 := LAYER_BIG
 13 [  9]: SETTABLE  R0 R1 R2     ; R0[R1] := R2
 14 [ 10]: GETGLOBAL R1 K7        ; R1 := SPRITE_ROBE_IDs
 15 [ 10]: GETTABLE  R1 R1 K9     ; R1 := R1["ROBE_BAG_OF_ADVENTURER"]
 16 [ 10]: GETGLOBAL R2 K5        ; R2 := LAYER_SMALL
 17 [ 10]: SETTABLE  R0 R1 R2     ; R0[R1] := R2
 18 [ 11]: SETGLOBAL R0 K6        ; LayerSizeTypeList := R0
 19 [ 13]: NEWTABLE  R0 0 0       ; R0 := {}
 20 [ 15]: GETGLOBAL R1 K11       ; R1 := JOBID
 21 [ 15]: GETTABLE  R1 R1 K12    ; R1 := R1["JT_NOVICE_H"]
 22 [ 15]: GETGLOBAL R2 K11       ; R2 := JOBID
 23 [ 15]: GETTABLE  R2 R2 K13    ; R2 := R2["JT_NOVICE"]
 24 [ 15]: SETTABLE  R0 R1 R2     ; R0[R1] := R2
 25 [ 16]: GETGLOBAL R1 K11       ; R1 := JOBID
 26 [ 16]: GETTABLE  R1 R1 K14    ; R1 := R1["JT_SWORDMAN_H"]
 27 [ 16]: GETGLOBAL R2 K11       ; R2 := JOBID
 28 [ 16]: GETTABLE  R2 R2 K15    ; R2 := R2["JT_SWORDMAN"]
 29 [ 16]: SETTABLE  R0 R1 R2     ; R0[R1] := R2
 30 [ 17]: GETGLOBAL R1 K11       ; R1 := JOBID
 31 [ 17]: GETTABLE  R1 R1 K16    ; R1 := R1["JT_MAGICIAN_H"]
 32 [ 17]: GETGLOBAL R2 K11       ; R2 := JOBID
 33 [ 17]: GETTABLE  R2 R2 K17    ; R2 := R2["JT_MAGICIAN"]
 34 [ 17]: SETTABLE  R0 R1 R2     ; R0[R1] := R2
 35 [ 18]: GETGLOBAL R1 K11       ; R1 := JOBID
 36 [ 18]: GETTABLE  R1 R1 K18    ; R1 := R1["JT_MERCHANT_H"]
 37 [ 18]: GETGLOBAL R2 K11       ; R2 := JOBID
 38 [ 18]: GETTABLE  R2 R2 K19    ; R2 := R2["JT_MERCHANT"]
 39 [ 18]: SETTABLE  R0 R1 R2     ; R0[R1] := R2
 40 [ 19]: GETGLOBAL R1 K11       ; R1 := JOBID
 41 [ 19]: GETTABLE  R1 R1 K20    ; R1 := R1["JT_ARCHER_H"]
 42 [ 19]: GETGLOBAL R2 K11       ; R2 := JOBID
 43 [ 19]: GETTABLE  R2 R2 K21    ; R2 := R2["JT_ARCHER"]
 44 [ 19]: SETTABLE  R0 R1 R2     ; R0[R1] := R2
 45 [ 20]: GETGLOBAL R1 K11       ; R1 := JOBID
 46 [ 20]: GETTABLE  R1 R1 K22    ; R1 := R1["JT_ACOLYTE_H"]
 47 [ 20]: GETGLOBAL R2 K11       ; R2 := JOBID
 48 [ 20]: GETTABLE  R2 R2 K23    ; R2 := R2["JT_ACOLYTE"]
 49 [ 20]: SETTABLE  R0 R1 R2     ; R0[R1] := R2
 50 [ 21]: GETGLOBAL R1 K11       ; R1 := JOBID
 51 [ 21]: GETTABLE  R1 R1 K24    ; R1 := R1["JT_THIEF_H"]
 52 [ 21]: GETGLOBAL R2 K11       ; R2 := JOBID
 53 [ 21]: GETTABLE  R2 R2 K25    ; R2 := R2["JT_THIEF"]
 54 [ 21]: SETTABLE  R0 R1 R2     ; R0[R1] := R2
 55 [ 22]: GETGLOBAL R1 K11       ; R1 := JOBID
 56 [ 22]: GETTABLE  R1 R1 K26    ; R1 := R1["JT_SUPERNOVICE2"]
 57 [ 22]: GETGLOBAL R2 K11       ; R2 := JOBID
 58 [ 22]: GETTABLE  R2 R2 K27    ; R2 := R2["JT_SUPERNOVICE"]
 59 [ 22]: SETTABLE  R0 R1 R2     ; R0[R1] := R2
 60 [ 24]: GETGLOBAL R1 K11       ; R1 := JOBID
 61 [ 24]: GETTABLE  R1 R1 K28    ; R1 := R1["JT_NOVICE_B"]
 62 [ 24]: GETGLOBAL R2 K11       ; R2 := JOBID
 63 [ 24]: GETTABLE  R2 R2 K13    ; R2 := R2["JT_NOVICE"]
 64 [ 24]: SETTABLE  R0 R1 R2     ; R0[R1] := R2
 65 [ 25]: GETGLOBAL R1 K11       ; R1 := JOBID
 66 [ 25]: GETTABLE  R1 R1 K29    ; R1 := R1["JT_SWORDMAN_B"]
 67 [ 25]: GETGLOBAL R2 K11       ; R2 := JOBID
 68 [ 25]: GETTABLE  R2 R2 K15    ; R2 := R2["JT_SWORDMAN"]
 69 [ 25]: SETTABLE  R0 R1 R2     ; R0[R1] := R2
 70 [ 26]: GETGLOBAL R1 K11       ; R1 := JOBID
 71 [ 26]: GETTABLE  R1 R1 K30    ; R1 := R1["JT_MAGICIAN_B"]
 72 [ 26]: GETGLOBAL R2 K11       ; R2 := JOBID
 73 [ 26]: GETTABLE  R2 R2 K17    ; R2 := R2["JT_MAGICIAN"]
 74 [ 26]: SETTABLE  R0 R1 R2     ; R0[R1] := R2
 75 [ 27]: GETGLOBAL R1 K11       ; R1 := JOBID
 76 [ 27]: GETTABLE  R1 R1 K31    ; R1 := R1["JT_ARCHER_B"]
 77 [ 27]: GETGLOBAL R2 K11       ; R2 := JOBID
 78 [ 27]: GETTABLE  R2 R2 K21    ; R2 := R2["JT_ARCHER"]
 79 [ 27]: SETTABLE  R0 R1 R2     ; R0[R1] := R2
 80 [ 28]: GETGLOBAL R1 K11       ; R1 := JOBID
 81 [ 28]: GETTABLE  R1 R1 K32    ; R1 := R1["JT_ACOLYTE_B"]
 82 [ 28]: GETGLOBAL R2 K11       ; R2 := JOBID
 83 [ 28]: GETTABLE  R2 R2 K23    ; R2 := R2["JT_ACOLYTE"]
 84 [ 28]: SETTABLE  R0 R1 R2     ; R0[R1] := R2
 85 [ 29]: GETGLOBAL R1 K11       ; R1 := JOBID
 86 [ 29]: GETTABLE  R1 R1 K33    ; R1 := R1["JT_MERCHANT_B"]
 87 [ 29]: GETGLOBAL R2 K11       ; R2 := JOBID
 88 [ 29]: GETTABLE  R2 R2 K19    ; R2 := R2["JT_MERCHANT"]
 89 [ 29]: SETTABLE  R0 R1 R2     ; R0[R1] := R2
 90 [ 30]: GETGLOBAL R1 K11       ; R1 := JOBID
 91 [ 30]: GETTABLE  R1 R1 K34    ; R1 := R1["JT_THIEF_B"]
 92 [ 30]: GETGLOBAL R2 K11       ; R2 := JOBID
 93 [ 30]: GETTABLE  R2 R2 K25    ; R2 := R2["JT_THIEF"]
 94 [ 30]: SETTABLE  R0 R1 R2     ; R0[R1] := R2
 95 [ 31]: GETGLOBAL R1 K11       ; R1 := JOBID
 96 [ 31]: GETTABLE  R1 R1 K35    ; R1 := R1["JT_KNIGHT_B"]
 97 [ 31]: GETGLOBAL R2 K11       ; R2 := JOBID
 98 [ 31]: GETTABLE  R2 R2 K36    ; R2 := R2["JT_KNIGHT"]
 99 [ 31]: SETTABLE  R0 R1 R2     ; R0[R1] := R2
100 [ 32]: GETGLOBAL R1 K11       ; R1 := JOBID
101 [ 32]: GETTABLE  R1 R1 K37    ; R1 := R1["JT_PRIEST_B"]
102 [ 32]: GETGLOBAL R2 K11       ; R2 := JOBID
103 [ 32]: GETTABLE  R2 R2 K38    ; R2 := R2["JT_PRIEST"]
104 [ 32]: SETTABLE  R0 R1 R2     ; R0[R1] := R2
105 [ 33]: GETGLOBAL R1 K11       ; R1 := JOBID
106 [ 33]: GETTABLE  R1 R1 K39    ; R1 := R1["JT_WIZARD_B"]
107 [ 33]: GETGLOBAL R2 K11       ; R2 := JOBID
108 [ 33]: GETTABLE  R2 R2 K40    ; R2 := R2["JT_WIZARD"]
109 [ 33]: SETTABLE  R0 R1 R2     ; R0[R1] := R2
110 [ 34]: GETGLOBAL R1 K11       ; R1 := JOBID
111 [ 34]: GETTABLE  R1 R1 K41    ; R1 := R1["JT_BLACKSMITH_B"]
112 [ 34]: GETGLOBAL R2 K11       ; R2 := JOBID
113 [ 34]: GETTABLE  R2 R2 K42    ; R2 := R2["JT_BLACKSMITH"]
114 [ 34]: SETTABLE  R0 R1 R2     ; R0[R1] := R2
115 [ 35]: GETGLOBAL R1 K11       ; R1 := JOBID
116 [ 35]: GETTABLE  R1 R1 K43    ; R1 := R1["JT_HUNTER_B"]
117 [ 35]: GETGLOBAL R2 K11       ; R2 := JOBID
118 [ 35]: GETTABLE  R2 R2 K44    ; R2 := R2["JT_HUNTER"]
119 [ 35]: SETTABLE  R0 R1 R2     ; R0[R1] := R2
120 [ 36]: GETGLOBAL R1 K11       ; R1 := JOBID
121 [ 36]: GETTABLE  R1 R1 K45    ; R1 := R1["JT_ASSASSIN_B"]
122 [ 36]: GETGLOBAL R2 K11       ; R2 := JOBID
123 [ 36]: GETTABLE  R2 R2 K46    ; R2 := R2["JT_ASSASSIN"]
124 [ 36]: SETTABLE  R0 R1 R2     ; R0[R1] := R2
125 [ 37]: GETGLOBAL R1 K11       ; R1 := JOBID
126 [ 37]: GETTABLE  R1 R1 K47    ; R1 := R1["JT_CRUSADER_B"]
127 [ 37]: GETGLOBAL R2 K11       ; R2 := JOBID
128 [ 37]: GETTABLE  R2 R2 K48    ; R2 := R2["JT_CRUSADER"]
129 [ 37]: SETTABLE  R0 R1 R2     ; R0[R1] := R2
130 [ 38]: GETGLOBAL R1 K11       ; R1 := JOBID
131 [ 38]: GETTABLE  R1 R1 K49    ; R1 := R1["JT_MONK_B"]
132 [ 38]: GETGLOBAL R2 K11       ; R2 := JOBID
133 [ 38]: GETTABLE  R2 R2 K50    ; R2 := R2["JT_MONK"]
134 [ 38]: SETTABLE  R0 R1 R2     ; R0[R1] := R2
135 [ 39]: GETGLOBAL R1 K11       ; R1 := JOBID
136 [ 39]: GETTABLE  R1 R1 K51    ; R1 := R1["JT_SAGE_B"]
137 [ 39]: GETGLOBAL R2 K11       ; R2 := JOBID
138 [ 39]: GETTABLE  R2 R2 K52    ; R2 := R2["JT_SAGE"]
139 [ 39]: SETTABLE  R0 R1 R2     ; R0[R1] := R2
140 [ 40]: GETGLOBAL R1 K11       ; R1 := JOBID
141 [ 40]: GETTABLE  R1 R1 K53    ; R1 := R1["JT_ROGUE_B"]
142 [ 40]: GETGLOBAL R2 K11       ; R2 := JOBID
143 [ 40]: GETTABLE  R2 R2 K54    ; R2 := R2["JT_ROGUE"]
144 [ 40]: SETTABLE  R0 R1 R2     ; R0[R1] := R2
145 [ 41]: GETGLOBAL R1 K11       ; R1 := JOBID
146 [ 41]: GETTABLE  R1 R1 K55    ; R1 := R1["JT_ALCHEMIST_B"]
147 [ 41]: GETGLOBAL R2 K11       ; R2 := JOBID
148 [ 41]: GETTABLE  R2 R2 K56    ; R2 := R2["JT_ALCHEMIST"]
149 [ 41]: SETTABLE  R0 R1 R2     ; R0[R1] := R2
150 [ 42]: GETGLOBAL R1 K11       ; R1 := JOBID
151 [ 42]: GETTABLE  R1 R1 K57    ; R1 := R1["JT_BARD_B"]
152 [ 42]: GETGLOBAL R2 K11       ; R2 := JOBID
153 [ 42]: GETTABLE  R2 R2 K58    ; R2 := R2["JT_BARD"]
154 [ 42]: SETTABLE  R0 R1 R2     ; R0[R1] := R2
155 [ 43]: GETGLOBAL R1 K11       ; R1 := JOBID
156 [ 43]: GETTABLE  R1 R1 K59    ; R1 := R1["JT_DANCER_B"]
157 [ 43]: GETGLOBAL R2 K11       ; R2 := JOBID
158 [ 43]: GETTABLE  R2 R2 K60    ; R2 := R2["JT_DANCER"]
159 [ 43]: SETTABLE  R0 R1 R2     ; R0[R1] := R2
160 [ 44]: GETGLOBAL R1 K11       ; R1 := JOBID
161 [ 44]: GETTABLE  R1 R1 K61    ; R1 := R1["JT_SUPERNOVICE_B"]
162 [ 44]: GETGLOBAL R2 K11       ; R2 := JOBID
163 [ 44]: GETTABLE  R2 R2 K27    ; R2 := R2["JT_SUPERNOVICE"]
164 [ 44]: SETTABLE  R0 R1 R2     ; R0[R1] := R2
165 [ 45]: GETGLOBAL R1 K11       ; R1 := JOBID
166 [ 45]: GETTABLE  R1 R1 K62    ; R1 := R1["JT_RUNE_KNIGHT_B"]
167 [ 45]: GETGLOBAL R2 K11       ; R2 := JOBID
168 [ 45]: GETTABLE  R2 R2 K63    ; R2 := R2["JT_RUNE_KNIGHT"]
169 [ 45]: SETTABLE  R0 R1 R2     ; R0[R1] := R2
170 [ 46]: GETGLOBAL R1 K11       ; R1 := JOBID
171 [ 46]: GETTABLE  R1 R1 K64    ; R1 := R1["JT_WARLOCK_B"]
172 [ 46]: GETGLOBAL R2 K11       ; R2 := JOBID
173 [ 46]: GETTABLE  R2 R2 K65    ; R2 := R2["JT_WARLOCK"]
174 [ 46]: SETTABLE  R0 R1 R2     ; R0[R1] := R2
175 [ 47]: GETGLOBAL R1 K11       ; R1 := JOBID
176 [ 47]: GETTABLE  R1 R1 K66    ; R1 := R1["JT_RANGER_B"]
177 [ 47]: GETGLOBAL R2 K11       ; R2 := JOBID
178 [ 47]: GETTABLE  R2 R2 K67    ; R2 := R2["JT_RANGER"]
179 [ 47]: SETTABLE  R0 R1 R2     ; R0[R1] := R2
180 [ 48]: GETGLOBAL R1 K11       ; R1 := JOBID
181 [ 48]: GETTABLE  R1 R1 K68    ; R1 := R1["JT_ARCHBISHOP_B"]
182 [ 48]: GETGLOBAL R2 K11       ; R2 := JOBID
183 [ 48]: GETTABLE  R2 R2 K69    ; R2 := R2["JT_ARCHBISHOP"]
184 [ 48]: SETTABLE  R0 R1 R2     ; R0[R1] := R2
185 [ 49]: GETGLOBAL R1 K11       ; R1 := JOBID
186 [ 49]: GETTABLE  R1 R1 K70    ; R1 := R1["JT_MECHANIC_B"]
187 [ 49]: GETGLOBAL R2 K11       ; R2 := JOBID
188 [ 49]: GETTABLE  R2 R2 K71    ; R2 := R2["JT_MECHANIC"]
189 [ 49]: SETTABLE  R0 R1 R2     ; R0[R1] := R2
190 [ 50]: GETGLOBAL R1 K11       ; R1 := JOBID
191 [ 50]: GETTABLE  R1 R1 K72    ; R1 := R1["JT_GUILLOTINE_CROSS_B"]
192 [ 50]: GETGLOBAL R2 K11       ; R2 := JOBID
193 [ 50]: GETTABLE  R2 R2 K73    ; R2 := R2["JT_GUILLOTINE_CROSS"]
194 [ 50]: SETTABLE  R0 R1 R2     ; R0[R1] := R2
195 [ 51]: GETGLOBAL R1 K11       ; R1 := JOBID
196 [ 51]: GETTABLE  R1 R1 K74    ; R1 := R1["JT_ROYAL_GUARD_B"]
197 [ 51]: GETGLOBAL R2 K11       ; R2 := JOBID
198 [ 51]: GETTABLE  R2 R2 K75    ; R2 := R2["JT_ROYAL_GUARD"]
199 [ 51]: SETTABLE  R0 R1 R2     ; R0[R1] := R2
200 [ 52]: GETGLOBAL R1 K11       ; R1 := JOBID
201 [ 52]: GETTABLE  R1 R1 K76    ; R1 := R1["JT_SORCERER_B"]
202 [ 52]: GETGLOBAL R2 K11       ; R2 := JOBID
203 [ 52]: GETTABLE  R2 R2 K77    ; R2 := R2["JT_SORCERER"]
204 [ 52]: SETTABLE  R0 R1 R2     ; R0[R1] := R2
205 [ 53]: GETGLOBAL R1 K11       ; R1 := JOBID
206 [ 53]: GETTABLE  R1 R1 K78    ; R1 := R1["JT_MINSTREL_B"]
207 [ 53]: GETGLOBAL R2 K11       ; R2 := JOBID
208 [ 53]: GETTABLE  R2 R2 K79    ; R2 := R2["JT_MINSTREL"]
209 [ 53]: SETTABLE  R0 R1 R2     ; R0[R1] := R2
210 [ 54]: GETGLOBAL R1 K11       ; R1 := JOBID
211 [ 54]: GETTABLE  R1 R1 K80    ; R1 := R1["JT_WANDERER_B"]
212 [ 54]: GETGLOBAL R2 K11       ; R2 := JOBID
213 [ 54]: GETTABLE  R2 R2 K81    ; R2 := R2["JT_WANDERER"]
214 [ 54]: SETTABLE  R0 R1 R2     ; R0[R1] := R2
215 [ 55]: GETGLOBAL R1 K11       ; R1 := JOBID
216 [ 55]: GETTABLE  R1 R1 K82    ; R1 := R1["JT_SURA_B"]
217 [ 55]: GETGLOBAL R2 K11       ; R2 := JOBID
218 [ 55]: GETTABLE  R2 R2 K83    ; R2 := R2["JT_SURA"]
219 [ 55]: SETTABLE  R0 R1 R2     ; R0[R1] := R2
220 [ 56]: GETGLOBAL R1 K11       ; R1 := JOBID
221 [ 56]: GETTABLE  R1 R1 K84    ; R1 := R1["JT_GENETIC_B"]
222 [ 56]: GETGLOBAL R2 K11       ; R2 := JOBID
223 [ 56]: GETTABLE  R2 R2 K85    ; R2 := R2["JT_GENETIC"]
224 [ 56]: SETTABLE  R0 R1 R2     ; R0[R1] := R2
225 [ 57]: GETGLOBAL R1 K11       ; R1 := JOBID
226 [ 57]: GETTABLE  R1 R1 K86    ; R1 := R1["JT_SHADOW_CHASER_B"]
227 [ 57]: GETGLOBAL R2 K11       ; R2 := JOBID
228 [ 57]: GETTABLE  R2 R2 K87    ; R2 := R2["JT_SHADOW_CHASER"]
229 [ 57]: SETTABLE  R0 R1 R2     ; R0[R1] := R2
230 [ 58]: GETGLOBAL R1 K11       ; R1 := JOBID
231 [ 58]: GETTABLE  R1 R1 K88    ; R1 := R1["JT_SUPERNOVICE2_B"]
232 [ 58]: GETGLOBAL R2 K11       ; R2 := JOBID
233 [ 58]: GETTABLE  R2 R2 K26    ; R2 := R2["JT_SUPERNOVICE2"]
234 [ 58]: SETTABLE  R0 R1 R2     ; R0[R1] := R2
235 [ 59]: SETGLOBAL R0 K10       ; SPRITE_INHERIT_LIST := R0
236 [ 61]: NEWTABLE  R0 0 0       ; R0 := {}
237 [ 64]: GETGLOBAL R1 K11       ; R1 := JOBID
238 [ 64]: GETTABLE  R1 R1 K73    ; R1 := R1["JT_GUILLOTINE_CROSS"]
239 [ 64]: GETGLOBAL R2 K11       ; R2 := JOBID
240 [ 64]: GETTABLE  R2 R2 K46    ; R2 := R2["JT_ASSASSIN"]
241 [ 64]: SETTABLE  R0 R1 R2     ; R0[R1] := R2
242 [ 67]: GETGLOBAL R1 K11       ; R1 := JOBID
243 [ 67]: GETTABLE  R1 R1 K90    ; R1 := R1["JT_ALCHEMIST_H"]
244 [ 67]: GETGLOBAL R2 K11       ; R2 := JOBID
245 [ 67]: GETTABLE  R2 R2 K56    ; R2 := R2["JT_ALCHEMIST"]
246 [ 67]: SETTABLE  R0 R1 R2     ; R0[R1] := R2
247 [ 68]: GETGLOBAL R1 K11       ; R1 := JOBID
248 [ 68]: GETTABLE  R1 R1 K85    ; R1 := R1["JT_GENETIC"]
249 [ 68]: GETGLOBAL R2 K11       ; R2 := JOBID
250 [ 68]: GETTABLE  R2 R2 K56    ; R2 := R2["JT_ALCHEMIST"]
251 [ 68]: SETTABLE  R0 R1 R2     ; R0[R1] := R2
252 [ 71]: GETGLOBAL R1 K11       ; R1 := JOBID
253 [ 71]: GETTABLE  R1 R1 K91    ; R1 := R1["JT_DANCER_H"]
254 [ 71]: GETGLOBAL R2 K11       ; R2 := JOBID
255 [ 71]: GETTABLE  R2 R2 K60    ; R2 := R2["JT_DANCER"]
256 [ 71]: SETTABLE  R0 R1 R2     ; R0[R1] := R2
257 [ 72]: GETGLOBAL R1 K11       ; R1 := JOBID
258 [ 72]: GETTABLE  R1 R1 K81    ; R1 := R1["JT_WANDERER"]
259 [ 72]: GETGLOBAL R2 K11       ; R2 := JOBID
260 [ 72]: GETTABLE  R2 R2 K60    ; R2 := R2["JT_DANCER"]
261 [ 72]: SETTABLE  R0 R1 R2     ; R0[R1] := R2
262 [ 75]: GETGLOBAL R1 K11       ; R1 := JOBID
263 [ 75]: GETTABLE  R1 R1 K92    ; R1 := R1["JT_BARD_H"]
264 [ 75]: GETGLOBAL R2 K11       ; R2 := JOBID
265 [ 75]: GETTABLE  R2 R2 K58    ; R2 := R2["JT_BARD"]
266 [ 75]: SETTABLE  R0 R1 R2     ; R0[R1] := R2
267 [ 76]: GETGLOBAL R1 K11       ; R1 := JOBID
268 [ 76]: GETTABLE  R1 R1 K79    ; R1 := R1["JT_MINSTREL"]
269 [ 76]: GETGLOBAL R2 K11       ; R2 := JOBID
270 [ 76]: GETTABLE  R2 R2 K58    ; R2 := R2["JT_BARD"]
271 [ 76]: SETTABLE  R0 R1 R2     ; R0[R1] := R2
272 [ 79]: GETGLOBAL R1 K11       ; R1 := JOBID
273 [ 79]: GETTABLE  R1 R1 K93    ; R1 := R1["JT_MONK_H"]
274 [ 79]: GETGLOBAL R2 K11       ; R2 := JOBID
275 [ 79]: GETTABLE  R2 R2 K50    ; R2 := R2["JT_MONK"]
276 [ 79]: SETTABLE  R0 R1 R2     ; R0[R1] := R2
277 [ 80]: GETGLOBAL R1 K11       ; R1 := JOBID
278 [ 80]: GETTABLE  R1 R1 K83    ; R1 := R1["JT_SURA"]
279 [ 80]: GETGLOBAL R2 K11       ; R2 := JOBID
280 [ 80]: GETTABLE  R2 R2 K50    ; R2 := R2["JT_MONK"]
281 [ 80]: SETTABLE  R0 R1 R2     ; R0[R1] := R2
282 [ 83]: GETGLOBAL R1 K11       ; R1 := JOBID
283 [ 83]: GETTABLE  R1 R1 K94    ; R1 := R1["JT_ROGUE_H"]
284 [ 83]: GETGLOBAL R2 K11       ; R2 := JOBID
285 [ 83]: GETTABLE  R2 R2 K54    ; R2 := R2["JT_ROGUE"]
286 [ 83]: SETTABLE  R0 R1 R2     ; R0[R1] := R2
287 [ 84]: GETGLOBAL R1 K11       ; R1 := JOBID
288 [ 84]: GETTABLE  R1 R1 K87    ; R1 := R1["JT_SHADOW_CHASER"]
289 [ 84]: GETGLOBAL R2 K11       ; R2 := JOBID
290 [ 84]: GETTABLE  R2 R2 K54    ; R2 := R2["JT_ROGUE"]
291 [ 84]: SETTABLE  R0 R1 R2     ; R0[R1] := R2
292 [ 87]: GETGLOBAL R1 K11       ; R1 := JOBID
293 [ 87]: GETTABLE  R1 R1 K95    ; R1 := R1["JT_KNIGHT_H"]
294 [ 87]: GETGLOBAL R2 K11       ; R2 := JOBID
295 [ 87]: GETTABLE  R2 R2 K36    ; R2 := R2["JT_KNIGHT"]
296 [ 87]: SETTABLE  R0 R1 R2     ; R0[R1] := R2
297 [ 90]: GETGLOBAL R1 K11       ; R1 := JOBID
298 [ 90]: GETTABLE  R1 R1 K69    ; R1 := R1["JT_ARCHBISHOP"]
299 [ 90]: GETGLOBAL R2 K11       ; R2 := JOBID
300 [ 90]: GETTABLE  R2 R2 K38    ; R2 := R2["JT_PRIEST"]
301 [ 90]: SETTABLE  R0 R1 R2     ; R0[R1] := R2
302 [ 93]: GETGLOBAL R1 K11       ; R1 := JOBID
303 [ 93]: GETTABLE  R1 R1 K96    ; R1 := R1["JT_PECO_GUNNER"]
304 [ 93]: GETGLOBAL R2 K11       ; R2 := JOBID
305 [ 93]: GETTABLE  R2 R2 K97    ; R2 := R2["JT_PECO_SWORD"]
306 [ 93]: SETTABLE  R0 R1 R2     ; R0[R1] := R2
307 [ 96]: GETGLOBAL R1 K11       ; R1 := JOBID
308 [ 96]: GETTABLE  R1 R1 K98    ; R1 := R1["JT_CRUSADER_H"]
309 [ 96]: GETGLOBAL R2 K11       ; R2 := JOBID
310 [ 96]: GETTABLE  R2 R2 K48    ; R2 := R2["JT_CRUSADER"]
311 [ 96]: SETTABLE  R0 R1 R2     ; R0[R1] := R2
312 [ 99]: GETGLOBAL R1 K11       ; R1 := JOBID
313 [ 99]: GETTABLE  R1 R1 K71    ; R1 := R1["JT_MECHANIC"]
314 [ 99]: GETGLOBAL R2 K11       ; R2 := JOBID
315 [ 99]: GETTABLE  R2 R2 K42    ; R2 := R2["JT_BLACKSMITH"]
316 [ 99]: SETTABLE  R0 R1 R2     ; R0[R1] := R2
317 [102]: GETGLOBAL R1 K11       ; R1 := JOBID
318 [102]: GETTABLE  R1 R1 K99    ; R1 := R1["JT_WIZARD_H"]
319 [102]: GETGLOBAL R2 K11       ; R2 := JOBID
320 [102]: GETTABLE  R2 R2 K40    ; R2 := R2["JT_WIZARD"]
321 [102]: SETTABLE  R0 R1 R2     ; R0[R1] := R2
322 [103]: GETGLOBAL R1 K11       ; R1 := JOBID
323 [103]: GETTABLE  R1 R1 K65    ; R1 := R1["JT_WARLOCK"]
324 [103]: GETGLOBAL R2 K11       ; R2 := JOBID
325 [103]: GETTABLE  R2 R2 K40    ; R2 := R2["JT_WIZARD"]
326 [103]: SETTABLE  R0 R1 R2     ; R0[R1] := R2
327 [104]: SETGLOBAL R0 K89       ; EXCEPTION_SPRITE_INHERIT_LIST := R0
328 [106]: NEWTABLE  R0 0 0       ; R0 := {}
329 [109]: GETGLOBAL R1 K11       ; R1 := JOBID
330 [109]: GETTABLE  R1 R1 K101   ; R1 := R1["JT_PIG_WHITESMITH"]
331 [109]: GETGLOBAL R2 K11       ; R2 := JOBID
332 [109]: GETTABLE  R2 R2 K102   ; R2 := R2["JT_PIG_MERCHANT"]
333 [109]: SETTABLE  R0 R1 R2     ; R0[R1] := R2
334 [110]: GETGLOBAL R1 K11       ; R1 := JOBID
335 [110]: GETTABLE  R1 R1 K103   ; R1 := R1["JT_PIG_GENETIC"]
336 [110]: GETGLOBAL R2 K11       ; R2 := JOBID
337 [110]: GETTABLE  R2 R2 K102   ; R2 := R2["JT_PIG_MERCHANT"]
338 [110]: SETTABLE  R0 R1 R2     ; R0[R1] := R2
339 [111]: GETGLOBAL R1 K11       ; R1 := JOBID
340 [111]: GETTABLE  R1 R1 K104   ; R1 := R1["JT_PIG_CREATOR"]
341 [111]: GETGLOBAL R2 K11       ; R2 := JOBID
342 [111]: GETTABLE  R2 R2 K102   ; R2 := R2["JT_PIG_MERCHANT"]
343 [111]: SETTABLE  R0 R1 R2     ; R0[R1] := R2
344 [112]: GETGLOBAL R1 K11       ; R1 := JOBID
345 [112]: GETTABLE  R1 R1 K105   ; R1 := R1["JT_PIG_ALCHE"]
346 [112]: GETGLOBAL R2 K11       ; R2 := JOBID
347 [112]: GETTABLE  R2 R2 K102   ; R2 := R2["JT_PIG_MERCHANT"]
348 [112]: SETTABLE  R0 R1 R2     ; R0[R1] := R2
349 [113]: GETGLOBAL R1 K11       ; R1 := JOBID
350 [113]: GETTABLE  R1 R1 K106   ; R1 := R1["JT_PIG_BLACKSMITH"]
351 [113]: GETGLOBAL R2 K11       ; R2 := JOBID
352 [113]: GETTABLE  R2 R2 K102   ; R2 := R2["JT_PIG_MERCHANT"]
353 [113]: SETTABLE  R0 R1 R2     ; R0[R1] := R2
354 [114]: GETGLOBAL R1 K11       ; R1 := JOBID
355 [114]: GETTABLE  R1 R1 K107   ; R1 := R1["JT_PIG_MERCHANT_B"]
356 [114]: GETGLOBAL R2 K11       ; R2 := JOBID
357 [114]: GETTABLE  R2 R2 K102   ; R2 := R2["JT_PIG_MERCHANT"]
358 [114]: SETTABLE  R0 R1 R2     ; R0[R1] := R2
359 [115]: GETGLOBAL R1 K11       ; R1 := JOBID
360 [115]: GETTABLE  R1 R1 K108   ; R1 := R1["JT_PIG_GENETIC_B"]
361 [115]: GETGLOBAL R2 K11       ; R2 := JOBID
362 [115]: GETTABLE  R2 R2 K102   ; R2 := R2["JT_PIG_MERCHANT"]
363 [115]: SETTABLE  R0 R1 R2     ; R0[R1] := R2
364 [116]: GETGLOBAL R1 K11       ; R1 := JOBID
365 [116]: GETTABLE  R1 R1 K109   ; R1 := R1["JT_PIG_ALCHE_B"]
366 [116]: GETGLOBAL R2 K11       ; R2 := JOBID
367 [116]: GETTABLE  R2 R2 K102   ; R2 := R2["JT_PIG_MERCHANT"]
368 [116]: SETTABLE  R0 R1 R2     ; R0[R1] := R2
369 [117]: GETGLOBAL R1 K11       ; R1 := JOBID
370 [117]: GETTABLE  R1 R1 K110   ; R1 := R1["JT_PIG_MERCHANT_H"]
371 [117]: GETGLOBAL R2 K11       ; R2 := JOBID
372 [117]: GETTABLE  R2 R2 K102   ; R2 := R2["JT_PIG_MERCHANT"]
373 [117]: SETTABLE  R0 R1 R2     ; R0[R1] := R2
374 [118]: GETGLOBAL R1 K11       ; R1 := JOBID
375 [118]: GETTABLE  R1 R1 K111   ; R1 := R1["JT_PIG_BLACKSMITH_B"]
376 [118]: GETGLOBAL R2 K11       ; R2 := JOBID
377 [118]: GETTABLE  R2 R2 K102   ; R2 := R2["JT_PIG_MERCHANT"]
378 [118]: SETTABLE  R0 R1 R2     ; R0[R1] := R2
379 [121]: GETGLOBAL R1 K11       ; R1 := JOBID
380 [121]: GETTABLE  R1 R1 K112   ; R1 := R1["JT_SHEEP_ACO"]
381 [121]: GETGLOBAL R2 K11       ; R2 := JOBID
382 [121]: GETTABLE  R2 R2 K113   ; R2 := R2["JT_SHEEP_MONK"]
383 [121]: SETTABLE  R0 R1 R2     ; R0[R1] := R2
384 [122]: GETGLOBAL R1 K11       ; R1 := JOBID
385 [122]: GETTABLE  R1 R1 K114   ; R1 := R1["JT_SHEEP_SURA"]
386 [122]: GETGLOBAL R2 K11       ; R2 := JOBID
387 [122]: GETTABLE  R2 R2 K113   ; R2 := R2["JT_SHEEP_MONK"]
388 [122]: SETTABLE  R0 R1 R2     ; R0[R1] := R2
389 [123]: GETGLOBAL R1 K11       ; R1 := JOBID
390 [123]: GETTABLE  R1 R1 K115   ; R1 := R1["JT_SHEEP_ARCB"]
391 [123]: GETGLOBAL R2 K11       ; R2 := JOBID
392 [123]: GETTABLE  R2 R2 K113   ; R2 := R2["JT_SHEEP_MONK"]
393 [123]: SETTABLE  R0 R1 R2     ; R0[R1] := R2
394 [124]: GETGLOBAL R1 K11       ; R1 := JOBID
395 [124]: GETTABLE  R1 R1 K116   ; R1 := R1["JT_SHEEP_CHAMP"]
396 [124]: GETGLOBAL R2 K11       ; R2 := JOBID
397 [124]: GETTABLE  R2 R2 K113   ; R2 := R2["JT_SHEEP_MONK"]
398 [124]: SETTABLE  R0 R1 R2     ; R0[R1] := R2
399 [125]: GETGLOBAL R1 K11       ; R1 := JOBID
400 [125]: GETTABLE  R1 R1 K117   ; R1 := R1["JT_SHEEP_PRIEST"]
401 [125]: GETGLOBAL R2 K11       ; R2 := JOBID
402 [125]: GETTABLE  R2 R2 K113   ; R2 := R2["JT_SHEEP_MONK"]
403 [125]: SETTABLE  R0 R1 R2     ; R0[R1] := R2
404 [126]: GETGLOBAL R1 K11       ; R1 := JOBID
405 [126]: GETTABLE  R1 R1 K118   ; R1 := R1["JT_SHEEP_HPRIEST"]
406 [126]: GETGLOBAL R2 K11       ; R2 := JOBID
407 [126]: GETTABLE  R2 R2 K113   ; R2 := R2["JT_SHEEP_MONK"]
408 [126]: SETTABLE  R0 R1 R2     ; R0[R1] := R2
409 [127]: GETGLOBAL R1 K11       ; R1 := JOBID
410 [127]: GETTABLE  R1 R1 K119   ; R1 := R1["JT_SHEEP_ACO_B"]
411 [127]: GETGLOBAL R2 K11       ; R2 := JOBID
412 [127]: GETTABLE  R2 R2 K113   ; R2 := R2["JT_SHEEP_MONK"]
413 [127]: SETTABLE  R0 R1 R2     ; R0[R1] := R2
414 [128]: GETGLOBAL R1 K11       ; R1 := JOBID
415 [128]: GETTABLE  R1 R1 K120   ; R1 := R1["JT_SHEEP_MONK_B"]
416 [128]: GETGLOBAL R2 K11       ; R2 := JOBID
417 [128]: GETTABLE  R2 R2 K113   ; R2 := R2["JT_SHEEP_MONK"]
418 [128]: SETTABLE  R0 R1 R2     ; R0[R1] := R2
419 [129]: GETGLOBAL R1 K11       ; R1 := JOBID
420 [129]: GETTABLE  R1 R1 K121   ; R1 := R1["JT_SHEEP_ARCB_B"]
421 [129]: GETGLOBAL R2 K11       ; R2 := JOBID
422 [129]: GETTABLE  R2 R2 K113   ; R2 := R2["JT_SHEEP_MONK"]
423 [129]: SETTABLE  R0 R1 R2     ; R0[R1] := R2
424 [130]: GETGLOBAL R1 K11       ; R1 := JOBID
425 [130]: GETTABLE  R1 R1 K122   ; R1 := R1["JT_SHEEP_SURA_B"]
426 [130]: GETGLOBAL R2 K11       ; R2 := JOBID
427 [130]: GETTABLE  R2 R2 K113   ; R2 := R2["JT_SHEEP_MONK"]
428 [130]: SETTABLE  R0 R1 R2     ; R0[R1] := R2
429 [131]: GETGLOBAL R1 K11       ; R1 := JOBID
430 [131]: GETTABLE  R1 R1 K123   ; R1 := R1["JT_SHEEP_ACO_H"]
431 [131]: GETGLOBAL R2 K11       ; R2 := JOBID
432 [131]: GETTABLE  R2 R2 K113   ; R2 := R2["JT_SHEEP_MONK"]
433 [131]: SETTABLE  R0 R1 R2     ; R0[R1] := R2
434 [132]: GETGLOBAL R1 K11       ; R1 := JOBID
435 [132]: GETTABLE  R1 R1 K124   ; R1 := R1["JT_SHEEP_PRIEST_B"]
436 [132]: GETGLOBAL R2 K11       ; R2 := JOBID
437 [132]: GETTABLE  R2 R2 K113   ; R2 := R2["JT_SHEEP_MONK"]
438 [132]: SETTABLE  R0 R1 R2     ; R0[R1] := R2
439 [135]: GETGLOBAL R1 K11       ; R1 := JOBID
440 [135]: GETTABLE  R1 R1 K125   ; R1 := R1["JT_DOG_G_CROSS"]
441 [135]: GETGLOBAL R2 K11       ; R2 := JOBID
442 [135]: GETTABLE  R2 R2 K126   ; R2 := R2["JT_DOG_THIEF"]
443 [135]: SETTABLE  R0 R1 R2     ; R0[R1] := R2
444 [136]: GETGLOBAL R1 K11       ; R1 := JOBID
445 [136]: GETTABLE  R1 R1 K127   ; R1 := R1["JT_DOG_ROGUE"]
446 [136]: GETGLOBAL R2 K11       ; R2 := JOBID
447 [136]: GETTABLE  R2 R2 K126   ; R2 := R2["JT_DOG_THIEF"]
448 [136]: SETTABLE  R0 R1 R2     ; R0[R1] := R2
449 [137]: GETGLOBAL R1 K11       ; R1 := JOBID
450 [137]: GETTABLE  R1 R1 K128   ; R1 := R1["JT_DOG_CHASER"]
451 [137]: GETGLOBAL R2 K11       ; R2 := JOBID
452 [137]: GETTABLE  R2 R2 K126   ; R2 := R2["JT_DOG_THIEF"]
453 [137]: SETTABLE  R0 R1 R2     ; R0[R1] := R2
454 [138]: GETGLOBAL R1 K11       ; R1 := JOBID
455 [138]: GETTABLE  R1 R1 K129   ; R1 := R1["JT_DOG_STALKER"]
456 [138]: GETGLOBAL R2 K11       ; R2 := JOBID
457 [138]: GETTABLE  R2 R2 K126   ; R2 := R2["JT_DOG_THIEF"]
458 [138]: SETTABLE  R0 R1 R2     ; R0[R1] := R2
459 [139]: GETGLOBAL R1 K11       ; R1 := JOBID
460 [139]: GETTABLE  R1 R1 K130   ; R1 := R1["JT_DOG_ASSASSIN"]
461 [139]: GETGLOBAL R2 K11       ; R2 := JOBID
462 [139]: GETTABLE  R2 R2 K126   ; R2 := R2["JT_DOG_THIEF"]
463 [139]: SETTABLE  R0 R1 R2     ; R0[R1] := R2
464 [140]: GETGLOBAL R1 K11       ; R1 := JOBID
465 [140]: GETTABLE  R1 R1 K131   ; R1 := R1["JT_DOG_ASSA_X"]
466 [140]: GETGLOBAL R2 K11       ; R2 := JOBID
467 [140]: GETTABLE  R2 R2 K126   ; R2 := R2["JT_DOG_THIEF"]
468 [140]: SETTABLE  R0 R1 R2     ; R0[R1] := R2
469 [141]: GETGLOBAL R1 K11       ; R1 := JOBID
470 [141]: GETTABLE  R1 R1 K132   ; R1 := R1["JT_DOG_ASSASSIN_B"]
471 [141]: GETGLOBAL R2 K11       ; R2 := JOBID
472 [141]: GETTABLE  R2 R2 K126   ; R2 := R2["JT_DOG_THIEF"]
473 [141]: SETTABLE  R0 R1 R2     ; R0[R1] := R2
474 [142]: GETGLOBAL R1 K11       ; R1 := JOBID
475 [142]: GETTABLE  R1 R1 K133   ; R1 := R1["JT_DOG_ROGUE_B"]
476 [142]: GETGLOBAL R2 K11       ; R2 := JOBID
477 [142]: GETTABLE  R2 R2 K126   ; R2 := R2["JT_DOG_THIEF"]
478 [142]: SETTABLE  R0 R1 R2     ; R0[R1] := R2
479 [143]: GETGLOBAL R1 K11       ; R1 := JOBID
480 [143]: GETTABLE  R1 R1 K134   ; R1 := R1["JT_DOG_G_CROSS_B"]
481 [143]: GETGLOBAL R2 K11       ; R2 := JOBID
482 [143]: GETTABLE  R2 R2 K126   ; R2 := R2["JT_DOG_THIEF"]
483 [143]: SETTABLE  R0 R1 R2     ; R0[R1] := R2
484 [144]: GETGLOBAL R1 K11       ; R1 := JOBID
485 [144]: GETTABLE  R1 R1 K135   ; R1 := R1["JT_DOG_CHASER_B"]
486 [144]: GETGLOBAL R2 K11       ; R2 := JOBID
487 [144]: GETTABLE  R2 R2 K126   ; R2 := R2["JT_DOG_THIEF"]
488 [144]: SETTABLE  R0 R1 R2     ; R0[R1] := R2
489 [145]: GETGLOBAL R1 K11       ; R1 := JOBID
490 [145]: GETTABLE  R1 R1 K136   ; R1 := R1["JT_DOG_THIEF_H"]
491 [145]: GETGLOBAL R2 K11       ; R2 := JOBID
492 [145]: GETTABLE  R2 R2 K126   ; R2 := R2["JT_DOG_THIEF"]
493 [145]: SETTABLE  R0 R1 R2     ; R0[R1] := R2
494 [146]: GETGLOBAL R1 K11       ; R1 := JOBID
495 [146]: GETTABLE  R1 R1 K137   ; R1 := R1["JT_DOG_THIEF_B"]
496 [146]: GETGLOBAL R2 K11       ; R2 := JOBID
497 [146]: GETTABLE  R2 R2 K126   ; R2 := R2["JT_DOG_THIEF"]
498 [146]: SETTABLE  R0 R1 R2     ; R0[R1] := R2
499 [149]: GETGLOBAL R1 K11       ; R1 := JOBID
500 [149]: GETTABLE  R1 R1 K138   ; R1 := R1["JT_OSTRICH_DANCER"]
501 [149]: GETGLOBAL R2 K11       ; R2 := JOBID
502 [149]: GETTABLE  R2 R2 K139   ; R2 := R2["JT_OSTRICH_ARCHER"]
503 [149]: SETTABLE  R0 R1 R2     ; R0[R1] := R2
504 [150]: GETGLOBAL R1 K11       ; R1 := JOBID
505 [150]: GETTABLE  R1 R1 K140   ; R1 := R1["JT_OSTRICH_MINSTREL"]
506 [150]: GETGLOBAL R2 K11       ; R2 := JOBID
507 [150]: GETTABLE  R2 R2 K139   ; R2 := R2["JT_OSTRICH_ARCHER"]
508 [150]: SETTABLE  R0 R1 R2     ; R0[R1] := R2
509 [151]: GETGLOBAL R1 K11       ; R1 := JOBID
510 [151]: GETTABLE  R1 R1 K141   ; R1 := R1["JT_OSTRICH_BARD"]
511 [151]: GETGLOBAL R2 K11       ; R2 := JOBID
512 [151]: GETTABLE  R2 R2 K139   ; R2 := R2["JT_OSTRICH_ARCHER"]
513 [151]: SETTABLE  R0 R1 R2     ; R0[R1] := R2
514 [152]: GETGLOBAL R1 K11       ; R1 := JOBID
515 [152]: GETTABLE  R1 R1 K142   ; R1 := R1["JT_OSTRICH_SNIPER"]
516 [152]: GETGLOBAL R2 K11       ; R2 := JOBID
517 [152]: GETTABLE  R2 R2 K139   ; R2 := R2["JT_OSTRICH_ARCHER"]
518 [152]: SETTABLE  R0 R1 R2     ; R0[R1] := R2
519 [153]: GETGLOBAL R1 K11       ; R1 := JOBID
520 [153]: GETTABLE  R1 R1 K143   ; R1 := R1["JT_OSTRICH_WANDER"]
521 [153]: GETGLOBAL R2 K11       ; R2 := JOBID
522 [153]: GETTABLE  R2 R2 K139   ; R2 := R2["JT_OSTRICH_ARCHER"]
523 [153]: SETTABLE  R0 R1 R2     ; R0[R1] := R2
524 [154]: GETGLOBAL R1 K11       ; R1 := JOBID
525 [154]: GETTABLE  R1 R1 K144   ; R1 := R1["JT_OSTRICH_ZIPSI"]
526 [154]: GETGLOBAL R2 K11       ; R2 := JOBID
527 [154]: GETTABLE  R2 R2 K139   ; R2 := R2["JT_OSTRICH_ARCHER"]
528 [154]: SETTABLE  R0 R1 R2     ; R0[R1] := R2
529 [155]: GETGLOBAL R1 K11       ; R1 := JOBID
530 [155]: GETTABLE  R1 R1 K145   ; R1 := R1["JT_OSTRICH_CROWN"]
531 [155]: GETGLOBAL R2 K11       ; R2 := JOBID
532 [155]: GETTABLE  R2 R2 K139   ; R2 := R2["JT_OSTRICH_ARCHER"]
533 [155]: SETTABLE  R0 R1 R2     ; R0[R1] := R2
534 [156]: GETGLOBAL R1 K11       ; R1 := JOBID
535 [156]: GETTABLE  R1 R1 K146   ; R1 := R1["JT_OSTRICH_HUNTER"]
536 [156]: GETGLOBAL R2 K11       ; R2 := JOBID
537 [156]: GETTABLE  R2 R2 K139   ; R2 := R2["JT_OSTRICH_ARCHER"]
538 [156]: SETTABLE  R0 R1 R2     ; R0[R1] := R2
539 [157]: GETGLOBAL R1 K11       ; R1 := JOBID
540 [157]: GETTABLE  R1 R1 K147   ; R1 := R1["JT_OSTRICH_ARCHER_B"]
541 [157]: GETGLOBAL R2 K11       ; R2 := JOBID
542 [157]: GETTABLE  R2 R2 K139   ; R2 := R2["JT_OSTRICH_ARCHER"]
543 [157]: SETTABLE  R0 R1 R2     ; R0[R1] := R2
544 [158]: GETGLOBAL R1 K11       ; R1 := JOBID
545 [158]: GETTABLE  R1 R1 K148   ; R1 := R1["JT_OSTRICH_HUNTER_B"]
546 [158]: GETGLOBAL R2 K11       ; R2 := JOBID
547 [158]: GETTABLE  R2 R2 K139   ; R2 := R2["JT_OSTRICH_ARCHER"]
548 [158]: SETTABLE  R0 R1 R2     ; R0[R1] := R2
549 [159]: GETGLOBAL R1 K11       ; R1 := JOBID
550 [159]: GETTABLE  R1 R1 K149   ; R1 := R1["JT_OSTRICH_BARD_B"]
551 [159]: GETGLOBAL R2 K11       ; R2 := JOBID
552 [159]: GETTABLE  R2 R2 K139   ; R2 := R2["JT_OSTRICH_ARCHER"]
553 [159]: SETTABLE  R0 R1 R2     ; R0[R1] := R2
554 [160]: GETGLOBAL R1 K11       ; R1 := JOBID
555 [160]: GETTABLE  R1 R1 K150   ; R1 := R1["JT_OSTRICH_DANCER_B"]
556 [160]: GETGLOBAL R2 K11       ; R2 := JOBID
557 [160]: GETTABLE  R2 R2 K139   ; R2 := R2["JT_OSTRICH_ARCHER"]
558 [160]: SETTABLE  R0 R1 R2     ; R0[R1] := R2
559 [161]: GETGLOBAL R1 K11       ; R1 := JOBID
560 [161]: GETTABLE  R1 R1 K151   ; R1 := R1["JT_OSTRICH_MINSTREL_B"]
561 [161]: GETGLOBAL R2 K11       ; R2 := JOBID
562 [161]: GETTABLE  R2 R2 K139   ; R2 := R2["JT_OSTRICH_ARCHER"]
563 [161]: SETTABLE  R0 R1 R2     ; R0[R1] := R2
564 [162]: GETGLOBAL R1 K11       ; R1 := JOBID
565 [162]: GETTABLE  R1 R1 K152   ; R1 := R1["JT_OSTRICH_WANDER_B"]
566 [162]: GETGLOBAL R2 K11       ; R2 := JOBID
567 [162]: GETTABLE  R2 R2 K139   ; R2 := R2["JT_OSTRICH_ARCHER"]
568 [162]: SETTABLE  R0 R1 R2     ; R0[R1] := R2
569 [163]: GETGLOBAL R1 K11       ; R1 := JOBID
570 [163]: GETTABLE  R1 R1 K153   ; R1 := R1["JT_OSTRICH_ARCHER_H"]
571 [163]: GETGLOBAL R2 K11       ; R2 := JOBID
572 [163]: GETTABLE  R2 R2 K139   ; R2 := R2["JT_OSTRICH_ARCHER"]
573 [163]: SETTABLE  R0 R1 R2     ; R0[R1] := R2
574 [166]: GETGLOBAL R1 K11       ; R1 := JOBID
575 [166]: GETTABLE  R1 R1 K154   ; R1 := R1["JT_FOX_SAGE"]
576 [166]: GETGLOBAL R2 K11       ; R2 := JOBID
577 [166]: GETTABLE  R2 R2 K155   ; R2 := R2["JT_FOX_MAGICIAN"]
578 [166]: SETTABLE  R0 R1 R2     ; R0[R1] := R2
579 [167]: GETGLOBAL R1 K11       ; R1 := JOBID
580 [167]: GETTABLE  R1 R1 K156   ; R1 := R1["JT_FOX_SORCERER"]
581 [167]: GETGLOBAL R2 K11       ; R2 := JOBID
582 [167]: GETTABLE  R2 R2 K155   ; R2 := R2["JT_FOX_MAGICIAN"]
583 [167]: SETTABLE  R0 R1 R2     ; R0[R1] := R2
584 [168]: GETGLOBAL R1 K11       ; R1 := JOBID
585 [168]: GETTABLE  R1 R1 K157   ; R1 := R1["JT_FOX_WARLOCK"]
586 [168]: GETGLOBAL R2 K11       ; R2 := JOBID
587 [168]: GETTABLE  R2 R2 K155   ; R2 := R2["JT_FOX_MAGICIAN"]
588 [168]: SETTABLE  R0 R1 R2     ; R0[R1] := R2
589 [169]: GETGLOBAL R1 K11       ; R1 := JOBID
590 [169]: GETTABLE  R1 R1 K158   ; R1 := R1["JT_FOX_WIZ"]
591 [169]: GETGLOBAL R2 K11       ; R2 := JOBID
592 [169]: GETTABLE  R2 R2 K155   ; R2 := R2["JT_FOX_MAGICIAN"]
593 [169]: SETTABLE  R0 R1 R2     ; R0[R1] := R2
594 [170]: GETGLOBAL R1 K11       ; R1 := JOBID
595 [170]: GETTABLE  R1 R1 K159   ; R1 := R1["JT_FOX_HWIZ"]
596 [170]: GETGLOBAL R2 K11       ; R2 := JOBID
597 [170]: GETTABLE  R2 R2 K155   ; R2 := R2["JT_FOX_MAGICIAN"]
598 [170]: SETTABLE  R0 R1 R2     ; R0[R1] := R2
599 [171]: GETGLOBAL R1 K11       ; R1 := JOBID
600 [171]: GETTABLE  R1 R1 K160   ; R1 := R1["JT_FOX_MAGICIAN_B"]
601 [171]: GETGLOBAL R2 K11       ; R2 := JOBID
602 [171]: GETTABLE  R2 R2 K155   ; R2 := R2["JT_FOX_MAGICIAN"]
603 [171]: SETTABLE  R0 R1 R2     ; R0[R1] := R2
604 [172]: GETGLOBAL R1 K11       ; R1 := JOBID
605 [172]: GETTABLE  R1 R1 K161   ; R1 := R1["JT_FOX_SAGE_B"]
606 [172]: GETGLOBAL R2 K11       ; R2 := JOBID
607 [172]: GETTABLE  R2 R2 K155   ; R2 := R2["JT_FOX_MAGICIAN"]
608 [172]: SETTABLE  R0 R1 R2     ; R0[R1] := R2
609 [173]: GETGLOBAL R1 K11       ; R1 := JOBID
610 [173]: GETTABLE  R1 R1 K162   ; R1 := R1["JT_FOX_WARLOCK_B"]
611 [173]: GETGLOBAL R2 K11       ; R2 := JOBID
612 [173]: GETTABLE  R2 R2 K155   ; R2 := R2["JT_FOX_MAGICIAN"]
613 [173]: SETTABLE  R0 R1 R2     ; R0[R1] := R2
614 [174]: GETGLOBAL R1 K11       ; R1 := JOBID
615 [174]: GETTABLE  R1 R1 K163   ; R1 := R1["JT_FOX_SORCERER_B"]
616 [174]: GETGLOBAL R2 K11       ; R2 := JOBID
617 [174]: GETTABLE  R2 R2 K155   ; R2 := R2["JT_FOX_MAGICIAN"]
618 [174]: SETTABLE  R0 R1 R2     ; R0[R1] := R2
619 [175]: GETGLOBAL R1 K11       ; R1 := JOBID
620 [175]: GETTABLE  R1 R1 K164   ; R1 := R1["JT_FOX_MAGICIAN_H"]
621 [175]: GETGLOBAL R2 K11       ; R2 := JOBID
622 [175]: GETTABLE  R2 R2 K155   ; R2 := R2["JT_FOX_MAGICIAN"]
623 [175]: SETTABLE  R0 R1 R2     ; R0[R1] := R2
624 [176]: GETGLOBAL R1 K11       ; R1 := JOBID
625 [176]: GETTABLE  R1 R1 K165   ; R1 := R1["JT_FOX_WIZ_B"]
626 [176]: GETGLOBAL R2 K11       ; R2 := JOBID
627 [176]: GETTABLE  R2 R2 K155   ; R2 := R2["JT_FOX_MAGICIAN"]
628 [176]: SETTABLE  R0 R1 R2     ; R0[R1] := R2
629 [179]: GETGLOBAL R1 K11       ; R1 := JOBID
630 [179]: GETTABLE  R1 R1 K166   ; R1 := R1["JT_PORING_STAR"]
631 [179]: GETGLOBAL R2 K11       ; R2 := JOBID
632 [179]: GETTABLE  R2 R2 K167   ; R2 := R2["JT_PORING_NOVICE"]
633 [179]: SETTABLE  R0 R1 R2     ; R0[R1] := R2
634 [180]: GETGLOBAL R1 K11       ; R1 := JOBID
635 [180]: GETTABLE  R1 R1 K168   ; R1 := R1["JT_PORING_SNOVICE"]
636 [180]: GETGLOBAL R2 K11       ; R2 := JOBID
637 [180]: GETTABLE  R2 R2 K167   ; R2 := R2["JT_PORING_NOVICE"]
638 [180]: SETTABLE  R0 R1 R2     ; R0[R1] := R2
639 [181]: GETGLOBAL R1 K11       ; R1 := JOBID
640 [181]: GETTABLE  R1 R1 K169   ; R1 := R1["JT_PORING_TAEKWON"]
641 [181]: GETGLOBAL R2 K11       ; R2 := JOBID
642 [181]: GETTABLE  R2 R2 K167   ; R2 := R2["JT_PORING_NOVICE"]
643 [181]: SETTABLE  R0 R1 R2     ; R0[R1] := R2
644 [182]: GETGLOBAL R1 K11       ; R1 := JOBID
645 [182]: GETTABLE  R1 R1 K170   ; R1 := R1["JT_PORING_NOVICE_B"]
646 [182]: GETGLOBAL R2 K11       ; R2 := JOBID
647 [182]: GETTABLE  R2 R2 K167   ; R2 := R2["JT_PORING_NOVICE"]
648 [182]: SETTABLE  R0 R1 R2     ; R0[R1] := R2
649 [183]: GETGLOBAL R1 K11       ; R1 := JOBID
650 [183]: GETTABLE  R1 R1 K171   ; R1 := R1["JT_PORING_SNOVICE_B"]
651 [183]: GETGLOBAL R2 K11       ; R2 := JOBID
652 [183]: GETTABLE  R2 R2 K167   ; R2 := R2["JT_PORING_NOVICE"]
653 [183]: SETTABLE  R0 R1 R2     ; R0[R1] := R2
654 [184]: GETGLOBAL R1 K11       ; R1 := JOBID
655 [184]: GETTABLE  R1 R1 K172   ; R1 := R1["JT_PORING_NOVICE_H"]
656 [184]: GETGLOBAL R2 K11       ; R2 := JOBID
657 [184]: GETTABLE  R2 R2 K167   ; R2 := R2["JT_PORING_NOVICE"]
658 [184]: SETTABLE  R0 R1 R2     ; R0[R1] := R2
659 [185]: GETGLOBAL R1 K11       ; R1 := JOBID
660 [185]: GETTABLE  R1 R1 K173   ; R1 := R1["JT_PORING_SNOVICE2"]
661 [185]: GETGLOBAL R2 K11       ; R2 := JOBID
662 [185]: GETTABLE  R2 R2 K167   ; R2 := R2["JT_PORING_NOVICE"]
663 [185]: SETTABLE  R0 R1 R2     ; R0[R1] := R2
664 [186]: GETGLOBAL R1 K11       ; R1 := JOBID
665 [186]: GETTABLE  R1 R1 K174   ; R1 := R1["JT_PORING_SNOVICE2_B"]
666 [186]: GETGLOBAL R2 K11       ; R2 := JOBID
667 [186]: GETTABLE  R2 R2 K167   ; R2 := R2["JT_PORING_NOVICE"]
668 [186]: SETTABLE  R0 R1 R2     ; R0[R1] := R2
669 [187]: SETGLOBAL R0 K100      ; RIDING_SPRITE_INHERIT_LIST := R0
670 [201]: CLOSURE   R0 0         ; R0 := closure(Function #0)
671 [189]: SETGLOBAL R0 K175      ; GetLayerSizeType := R0
672 [219]: CLOSURE   R0 1         ; R0 := closure(Function #1)
673 [203]: SETGLOBAL R0 K176      ; GetLayerDirTbl := R0
674 [251]: CLOSURE   R0 2         ; R0 := closure(Function #2)
675 [221]: SETGLOBAL R0 K177      ; GetSpriteInheriteJob := R0
676 [279]: CLOSURE   R0 3         ; R0 := closure(Function #3)
677 [253]: SETGLOBAL R0 K178      ; DrawOnTop := R0
678 [279]: RETURN    R0 1         ; return 


; Function #0:
;
; Name:            
; Defined at line: 189
; #Upvalues:       0
; #Parameters:     1 (R0)
; Is_vararg:       0
; Max Stack Size:  3
;
; Locals:
; Start PC |  End PC  | Name
; 00000000 | 0000000e | robeID
; 00000008 | 0000000e | sizeType
;
; No upvalues

  1 [190]: GETGLOBAL R1 K0        ; R1 := LayerSizeTypeList
  2 [190]: GETTABLE  R1 R1 R0     ; R1 := R1[R0]
  3 [190]: EQ        0 R1 K1      ; if R1 != nil then PC := 7
  4 [190]: JMP       7
  5 [191]: GETGLOBAL R1 K2        ; R1 := LAYER_BIG
  6 [191]: RETURN    R1 2         ; return R1
  7 [194]: GETGLOBAL R1 K0        ; R1 := LayerSizeTypeList
  8 [194]: GETTABLE  R1 R1 R0     ; R1 := R1[R0]
  9 [196]: EQ        1 R1 K1      ; if R1 == nil then PC := 13
 10 [196]: JMP       13
 11 [197]: RETURN    R1 2         ; return R1
 12 [197]: JMP       15           ; PC := 15
 13 [199]: GETGLOBAL R2 K2        ; R2 := LAYER_BIG
 14 [199]: RETURN    R2 2         ; return R2
 15 [201]: RETURN    R0 1         ; return 


; Function #1:
;
; Name:            
; Defined at line: 203
; #Upvalues:       0
; #Parameters:     2 (R0, R1)
; Is_vararg:       0
; Max Stack Size:  4
;
; Locals:
; Start PC |  End PC  | Name
; 00000000 | 0000001a | sex
; 00000000 | 0000001a | robeID
; 00000003 | 0000001a | sizeType
;
; No upvalues

  1 [204]: GETGLOBAL R2 K0        ; R2 := GetLayerSizeType
  2 [204]: MOVE      R3 R1        ; R3 := R1
  3 [204]: CALL      R2 2 2       ; R2 := R2(R3)
  4 [206]: GETGLOBAL R3 K1        ; R3 := LAYER_BIG
  5 [206]: EQ        0 R2 R3      ; if R2 != R3 then PC := 16
  6 [206]: JMP       16
  7 [207]: GETGLOBAL R3 K2        ; R3 := SEX_FEMALE
  8 [207]: EQ        0 R0 R3      ; if R0 != R3 then PC := 13
  9 [207]: JMP       13
 10 [208]: GETGLOBAL R3 K3        ; R3 := BigLayerDir_F
 11 [208]: RETURN    R3 2         ; return R3
 12 [208]: JMP       27           ; PC := 27
 13 [210]: GETGLOBAL R3 K4        ; R3 := BigLayerDir_M
 14 [210]: RETURN    R3 2         ; return R3
 15 [211]: JMP       27           ; PC := 27
 16 [212]: GETGLOBAL R3 K5        ; R3 := LAYER_SMALL
 17 [212]: EQ        0 R2 R3      ; if R2 != R3 then PC := 27
 18 [212]: JMP       27
 19 [213]: GETGLOBAL R3 K2        ; R3 := SEX_FEMALE
 20 [213]: EQ        0 R0 R3      ; if R0 != R3 then PC := 25
 21 [213]: JMP       25
 22 [214]: GETGLOBAL R3 K6        ; R3 := SmallLayerDir_F
 23 [214]: RETURN    R3 2         ; return R3
 24 [214]: JMP       27           ; PC := 27
 25 [216]: GETGLOBAL R3 K7        ; R3 := SmallLayerDir_M
 26 [216]: RETURN    R3 2         ; return R3
 27 [219]: RETURN    R0 1         ; return 


; Function #2:
;
; Name:            
; Defined at line: 221
; #Upvalues:       0
; #Parameters:     1 (R0)
; Is_vararg:       0
; Max Stack Size:  3
;
; Locals:
; Start PC |  End PC  | Name
; 00000000 | 0000002b | jobID
; 0000001e | 0000002b | sizeType
;
; No upvalues

  1 [222]: GETGLOBAL R1 K0        ; R1 := RIDING_SPRITE_INHERIT_LIST
  2 [222]: EQ        1 R1 K1      ; if R1 == nil then PC := 10
  3 [222]: JMP       10
  4 [223]: GETGLOBAL R1 K0        ; R1 := RIDING_SPRITE_INHERIT_LIST
  5 [223]: GETTABLE  R1 R1 R0     ; R1 := R1[R0]
  6 [223]: EQ        1 R1 K1      ; if R1 == nil then PC := 10
  7 [223]: JMP       10
  8 [224]: GETGLOBAL R1 K0        ; R1 := RIDING_SPRITE_INHERIT_LIST
  9 [224]: GETTABLE  R0 R1 R0     ; R0 := R1[R0]
 10 [228]: GETGLOBAL R1 K2        ; R1 := JOB_INHERIT_LIST2
 11 [228]: EQ        1 R1 K1      ; if R1 == nil then PC := 19
 12 [228]: JMP       19
 13 [229]: GETGLOBAL R1 K2        ; R1 := JOB_INHERIT_LIST2
 14 [229]: GETTABLE  R1 R1 R0     ; R1 := R1[R0]
 15 [229]: EQ        1 R1 K1      ; if R1 == nil then PC := 19
 16 [229]: JMP       19
 17 [230]: GETGLOBAL R1 K2        ; R1 := JOB_INHERIT_LIST2
 18 [230]: GETTABLE  R0 R1 R0     ; R0 := R1[R0]
 19 [234]: GETGLOBAL R1 K3        ; R1 := SPRITE_INHERIT_LIST
 20 [234]: EQ        1 R1 K1      ; if R1 == nil then PC := 28
 21 [234]: JMP       28
 22 [235]: GETGLOBAL R1 K3        ; R1 := SPRITE_INHERIT_LIST
 23 [235]: GETTABLE  R1 R1 R0     ; R1 := R1[R0]
 24 [235]: EQ        1 R1 K1      ; if R1 == nil then PC := 28
 25 [235]: JMP       28
 26 [236]: GETGLOBAL R1 K3        ; R1 := SPRITE_INHERIT_LIST
 27 [236]: GETTABLE  R0 R1 R0     ; R0 := R1[R0]
 28 [240]: GETGLOBAL R1 K4        ; R1 := GetLayerSizeType
 29 [240]: GETGLOBAL R2 K5        ; R2 := robeID
 30 [240]: CALL      R1 2 2       ; R1 := R1(R2)
 31 [242]: GETGLOBAL R2 K6        ; R2 := LAYER_BIG
 32 [242]: EQ        0 R1 R2      ; if R1 != R2 then PC := 43
 33 [242]: JMP       43
 34 [243]: GETGLOBAL R2 K7        ; R2 := EXCEPTION_SPRITE_INHERIT_LIST
 35 [243]: EQ        1 R2 K1      ; if R2 == nil then PC := 43
 36 [243]: JMP       43
 37 [244]: GETGLOBAL R2 K7        ; R2 := EXCEPTION_SPRITE_INHERIT_LIST
 38 [244]: GETTABLE  R2 R2 R0     ; R2 := R2[R0]
 39 [244]: EQ        1 R2 K1      ; if R2 == nil then PC := 43
 40 [244]: JMP       43
 41 [245]: GETGLOBAL R2 K7        ; R2 := EXCEPTION_SPRITE_INHERIT_LIST
 42 [245]: GETTABLE  R0 R2 R0     ; R0 := R2[R0]
 43 [250]: RETURN    R0 2         ; return R0
 44 [251]: RETURN    R0 1         ; return 


; Function #3:
;
; Name:            
; Defined at line: 253
; #Upvalues:       0
; #Parameters:     5 (R0, R1, R2, R3, R4)
; Is_vararg:       0
; Max Stack Size:  8
;
; Locals:
; Start PC |  End PC  | Name
; 00000000 | 0000002a | robeID
; 00000000 | 0000002a | sex
; 00000000 | 0000002a | jobID
; 00000000 | 0000002a | actNum
; 00000000 | 0000002a | motNum
; 00000004 | 0000002a | LayerDirTbl
; 00000016 | 0000002a | idx
;
; No upvalues

  1 [254]: GETGLOBAL R5 K0        ; R5 := GetLayerDirTbl
  2 [254]: MOVE      R6 R1        ; R6 := R1
  3 [254]: MOVE      R7 R0        ; R7 := R0
  4 [254]: CALL      R5 3 2       ; R5 := R5(R6,R7)
  5 [256]: GETGLOBAL R6 K1        ; R6 := GetSpriteInheriteJob
  6 [256]: MOVE      R7 R2        ; R7 := R2
  7 [256]: CALL      R6 2 2       ; R6 := R6(R7)
  8 [256]: MOVE      R2 R6        ; R2 := R6
  9 [258]: EQ        1 R5 K2      ; if R5 == nil then PC := 14
 10 [258]: JMP       14
 11 [258]: GETTABLE  R6 R5 R2     ; R6 := R5[R2]
 12 [258]: EQ        0 R6 K2      ; if R6 != nil then PC := 16
 13 [258]: JMP       16
 14 [259]: LOADBOOL  R6 1 0       ; R6 := true
 15 [259]: RETURN    R6 2         ; return R6
 16 [262]: GETTABLE  R6 R5 R2     ; R6 := R5[R2]
 17 [262]: GETTABLE  R6 R6 R3     ; R6 := R6[R3]
 18 [262]: EQ        0 R6 K2      ; if R6 != nil then PC := 22
 19 [262]: JMP       22
 20 [263]: LOADBOOL  R6 1 0       ; R6 := true
 21 [263]: RETURN    R6 2         ; return R6
 22 [266]: LOADK     R6 K3        ; R6 := 1
 23 [268]: GETTABLE  R7 R5 R2     ; R7 := R5[R2]
 24 [268]: GETTABLE  R7 R7 R3     ; R7 := R7[R3]
 25 [268]: GETTABLE  R7 R7 R6     ; R7 := R7[R6]
 26 [268]: SETGLOBAL R7 K4        ; motInfo := R7
 27 [269]: JMP       38           ; PC := 38
 28 [270]: GETGLOBAL R7 K4        ; R7 := motInfo
 29 [270]: EQ        0 R7 R4      ; if R7 != R4 then PC := 33
 30 [270]: JMP       33
 31 [271]: LOADBOOL  R7 0 0       ; R7 := false
 32 [271]: RETURN    R7 2         ; return R7
 33 [274]: ADD       R6 R6 K3     ; R6 := R6 + 1
 34 [275]: GETTABLE  R7 R5 R2     ; R7 := R5[R2]
 35 [275]: GETTABLE  R7 R7 R3     ; R7 := R7[R3]
 36 [275]: GETTABLE  R7 R7 R6     ; R7 := R7[R6]
 37 [275]: SETGLOBAL R7 K4        ; motInfo := R7
 38 [269]: GETGLOBAL R7 K4        ; R7 := motInfo
 39 [269]: EQ        0 R7 K2      ; if R7 != nil then PC := 28
 40 [269]: JMP       28
 41 [278]: LOADBOOL  R7 1 0       ; R7 := true
 42 [278]: RETURN    R7 2         ; return R7
 43 [279]: RETURN    R0 1         ; return 
