; This file has been disassembled by the Lua 5 disassembler by Mike Lankamp
;
; Original file: hotkey.lub
; File format:   Lua 5.0
; Disassembled:  Wed Mar 09 19:40:27 2011
;

; Name:            @hotkey.lua
; Defined at line: 0
; #Upvalues:       0
; #Parameters:     0
; Is_vararg:       0
; Max Stack Size:  5
;
; No locals information
; No upvalues

  1 [  9]: NEWTABLE  R0 0 0       ; R0 := {}
  2 [ 10]: SETTABLE  R0 K1 K2     ; R0[1] := "MB_L"
  3 [ 11]: SETTABLE  R0 K3 K4     ; R0[2] := "MB_R"
  4 [ 12]: SETTABLE  R0 K5 K6     ; R0[4] := "MB_C"
  5 [ 13]: SETTABLE  R0 K7 K8     ; R0[8] := "Back"
  6 [ 14]: SETTABLE  R0 K9 K10    ; R0[9] := "Tab"
  7 [ 15]: SETTABLE  R0 K11 K12   ; R0[12] := "Clear"
  8 [ 16]: SETTABLE  R0 K13 K14   ; R0[13] := "Return"
  9 [ 17]: SETTABLE  R0 K15 K16   ; R0[16] := "Shift"
 10 [ 18]: SETTABLE  R0 K17 K18   ; R0[17] := "Ctrl"
 11 [ 19]: SETTABLE  R0 K19 K20   ; R0[18] := "Alt"
 12 [ 20]: SETTABLE  R0 K21 K22   ; R0[19] := "Pause"
 13 [ 21]: SETTABLE  R0 K23 K24   ; R0[20] := "Caps"
 14 [ 22]: SETTABLE  R0 K25 K26   ; R0[21] := "Hangul"
 15 [ 23]: SETTABLE  R0 K27 K28   ; R0[25] := "Hanja"
 16 [ 25]: SETTABLE  R0 K29 K30   ; R0[32] := "Space"
 17 [ 26]: SETTABLE  R0 K31 K32   ; R0[33] := "Prior"
 18 [ 27]: SETTABLE  R0 K33 K34   ; R0[34] := "Next"
 19 [ 28]: SETTABLE  R0 K35 K36   ; R0[35] := "End"
 20 [ 29]: SETTABLE  R0 K37 K38   ; R0[36] := "Home"
 21 [ 30]: SETTABLE  R0 K39 K40   ; R0[37] := "Left"
 22 [ 31]: SETTABLE  R0 K41 K42   ; R0[38] := "Up"
 23 [ 32]: SETTABLE  R0 K43 K44   ; R0[39] := "Right"
 24 [ 33]: SETTABLE  R0 K45 K46   ; R0[40] := "Down"
 25 [ 34]: SETTABLE  R0 K47 K48   ; R0[41] := "Select"
 26 [ 35]: SETTABLE  R0 K49 K50   ; R0[43] := "Execute"
 27 [ 36]: SETTABLE  R0 K51 K52   ; R0[44] := "Snapshot"
 28 [ 37]: SETTABLE  R0 K53 K54   ; R0[45] := "Ins"
 29 [ 38]: SETTABLE  R0 K55 K56   ; R0[46] := "Del"
 30 [ 39]: SETTABLE  R0 K57 K58   ; R0[47] := "Help"
 31 [ 40]: SETTABLE  R0 K59 K60   ; R0[48] := "0"
 32 [ 41]: SETTABLE  R0 K61 K62   ; R0[49] := "1"
 33 [ 42]: SETTABLE  R0 K63 K64   ; R0[50] := "2"
 34 [ 43]: SETTABLE  R0 K65 K66   ; R0[51] := "3"
 35 [ 44]: SETTABLE  R0 K67 K68   ; R0[52] := "4"
 36 [ 45]: SETTABLE  R0 K69 K70   ; R0[53] := "5"
 37 [ 46]: SETTABLE  R0 K71 K72   ; R0[54] := "6"
 38 [ 47]: SETTABLE  R0 K73 K74   ; R0[55] := "7"
 39 [ 48]: SETTABLE  R0 K75 K76   ; R0[56] := "8"
 40 [ 49]: SETTABLE  R0 K77 K78   ; R0[57] := "9"
 41 [ 50]: SETTABLE  R0 K79 K80   ; R0[65] := "A"
 42 [ 51]: SETTABLE  R0 K81 K82   ; R0[66] := "B"
 43 [ 52]: SETTABLE  R0 K83 K84   ; R0[67] := "C"
 44 [ 53]: SETTABLE  R0 K85 K86   ; R0[68] := "D"
 45 [ 54]: SETTABLE  R0 K87 K88   ; R0[69] := "E"
 46 [ 55]: SETTABLE  R0 K89 K90   ; R0[70] := "F"
 47 [ 56]: SETTABLE  R0 K91 K92   ; R0[71] := "G"
 48 [ 57]: SETTABLE  R0 K93 K94   ; R0[72] := "H"
 49 [ 58]: SETTABLE  R0 K95 K96   ; R0[73] := "I"
 50 [ 59]: SETTABLE  R0 K97 K98   ; R0[74] := "J"
 51 [ 60]: SETTABLE  R0 K99 K100  ; R0[75] := "K"
 52 [ 61]: SETTABLE  R0 K101 K102 ; R0[76] := "L"
 53 [ 62]: SETTABLE  R0 K103 K104 ; R0[77] := "M"
 54 [ 63]: SETTABLE  R0 K105 K106 ; R0[78] := "N"
 55 [ 64]: SETTABLE  R0 K107 K108 ; R0[79] := "O"
 56 [ 65]: SETTABLE  R0 K109 K110 ; R0[80] := "P"
 57 [ 66]: SETTABLE  R0 K111 K112 ; R0[81] := "Q"
 58 [ 67]: SETTABLE  R0 K113 K114 ; R0[82] := "R"
 59 [ 68]: SETTABLE  R0 K115 K116 ; R0[83] := "S"
 60 [ 69]: SETTABLE  R0 K117 K118 ; R0[84] := "T"
 61 [ 70]: SETTABLE  R0 K119 K120 ; R0[85] := "U"
 62 [ 71]: SETTABLE  R0 K121 K122 ; R0[86] := "V"
 63 [ 72]: SETTABLE  R0 K123 K124 ; R0[87] := "W"
 64 [ 73]: SETTABLE  R0 K125 K126 ; R0[88] := "X"
 65 [ 74]: SETTABLE  R0 K127 K128 ; R0[89] := "Y"
 66 [ 75]: SETTABLE  R0 K129 K130 ; R0[90] := "Z"
 67 [ 78]: SETTABLE  R0 K131 K132 ; R0[93] := "Apps"
 68 [ 79]: SETTABLE  R0 K133 K134 ; R0[96] := "Num_0"
 69 [ 80]: SETTABLE  R0 K135 K136 ; R0[97] := "Num_1"
 70 [ 81]: SETTABLE  R0 K137 K138 ; R0[98] := "Num_2"
 71 [ 82]: SETTABLE  R0 K139 K140 ; R0[99] := "Num_3"
 72 [ 83]: SETTABLE  R0 K141 K142 ; R0[100] := "Num_4"
 73 [ 84]: SETTABLE  R0 K143 K144 ; R0[101] := "Num_5"
 74 [ 85]: SETTABLE  R0 K145 K146 ; R0[102] := "Num_6"
 75 [ 86]: SETTABLE  R0 K147 K148 ; R0[103] := "Num_7"
 76 [ 87]: SETTABLE  R0 K149 K150 ; R0[104] := "Num_8"
 77 [ 88]: SETTABLE  R0 K151 K152 ; R0[105] := "Num_9"
 78 [ 89]: SETTABLE  R0 K153 K154 ; R0[106] := "Multiply"
 79 [ 90]: SETTABLE  R0 K155 K156 ; R0[107] := "Add"
 80 [ 91]: SETTABLE  R0 K157 K158 ; R0[108] := "Sep"
 81 [ 92]: SETTABLE  R0 K159 K160 ; R0[109] := "Sub"
 82 [ 93]: SETTABLE  R0 K161 K162 ; R0[110] := "Decimal"
 83 [ 94]: SETTABLE  R0 K163 K164 ; R0[111] := "Devide"
 84 [ 95]: SETTABLE  R0 K165 K166 ; R0[112] := "F1"
 85 [ 96]: SETTABLE  R0 K167 K168 ; R0[113] := "F2"
 86 [ 97]: SETTABLE  R0 K169 K170 ; R0[114] := "F3"
 87 [ 98]: SETTABLE  R0 K171 K172 ; R0[115] := "F4"
 88 [ 99]: SETTABLE  R0 K173 K174 ; R0[116] := "F5"
 89 [100]: SETTABLE  R0 K175 K176 ; R0[117] := "F6"
 90 [101]: SETTABLE  R0 K177 K178 ; R0[118] := "F7"
 91 [102]: SETTABLE  R0 K179 K180 ; R0[119] := "F8"
 92 [103]: SETTABLE  R0 K181 K182 ; R0[120] := "F9"
 93 [104]: SETTABLE  R0 K183 K184 ; R0[121] := "F10"
 94 [105]: SETTABLE  R0 K185 K186 ; R0[122] := "F11"
 95 [106]: SETTABLE  R0 K187 K188 ; R0[123] := "F12"
 96 [107]: SETTABLE  R0 K189 K190 ; R0[124] := "F13"
 97 [108]: SETTABLE  R0 K191 K192 ; R0[125] := "F14"
 98 [109]: SETTABLE  R0 K193 K194 ; R0[126] := "F15"
 99 [110]: SETTABLE  R0 K195 K196 ; R0[127] := "F16"
100 [111]: SETTABLE  R0 K197 K198 ; R0[128] := "F17"
101 [112]: SETTABLE  R0 K199 K200 ; R0[129] := "F18"
102 [113]: SETTABLE  R0 K201 K202 ; R0[130] := "F19"
103 [114]: SETTABLE  R0 K203 K204 ; R0[131] := "F20"
104 [115]: SETTABLE  R0 K205 K206 ; R0[132] := "F21"
105 [116]: SETTABLE  R0 K207 K208 ; R0[133] := "F22"
106 [117]: SETTABLE  R0 K209 K210 ; R0[134] := "F23"
107 [118]: SETTABLE  R0 K211 K212 ; R0[135] := "F24"
108 [119]: SETTABLE  R0 K213 K214 ; R0[144] := "Num"
109 [120]: SETTABLE  R0 K215 K216 ; R0[145] := "Scroll"
110 [121]: SETTABLE  R0 K217 K218 ; R0[186] := ";"
111 [122]: SETTABLE  R0 K219 K220 ; R0[187] := "="
112 [123]: SETTABLE  R0 K221 K222 ; R0[188] := ","
113 [124]: SETTABLE  R0 K223 K224 ; R0[189] := "-"
114 [125]: SETTABLE  R0 K225 K226 ; R0[190] := "."
115 [126]: SETTABLE  R0 K227 K228 ; R0[191] := "/"
116 [127]: SETTABLE  R0 K229 K230 ; R0[192] := "`"
117 [128]: SETTABLE  R0 K231 K232 ; R0[219] := "["
118 [129]: SETTABLE  R0 K233 K234 ; R0[220] := "\\"
119 [130]: SETTABLE  R0 K235 K236 ; R0[221] := "]"
120 [131]: SETTABLE  R0 K237 K238 ; R0[222] := "\'"
121 [132]: SETGLOBAL R0 K0        ; KEYNAME := R0
122 [134]: NEWTABLE  R0 0 0       ; R0 := {}
123 [135]: NEWTABLE  R1 0 2       ; R1 := {}
124 [135]: GETGLOBAL R2 K242      ; R2 := MsgStrID
125 [135]: GETTABLE  R2 R2 K243   ; R2 := R2["MSI_HK_SKILLBAR1_1"]
126 [135]: SETTABLE  R1 K241 R2   ; R1["EXE"] := R2
127 [135]: SETTABLE  R1 K244 K165 ; R1["KEY1"] := 112
128 [135]: SETTABLE  R0 K240 R1   ; R0[0] := R1
129 [136]: NEWTABLE  R1 0 2       ; R1 := {}
130 [136]: GETGLOBAL R2 K242      ; R2 := MsgStrID
131 [136]: GETTABLE  R2 R2 K245   ; R2 := R2["MSI_HK_SKILLBAR1_2"]
132 [136]: SETTABLE  R1 K241 R2   ; R1["EXE"] := R2
133 [136]: SETTABLE  R1 K244 K167 ; R1["KEY1"] := 113
134 [136]: SETTABLE  R0 K1 R1     ; R0[1] := R1
135 [137]: NEWTABLE  R1 0 2       ; R1 := {}
136 [137]: GETGLOBAL R2 K242      ; R2 := MsgStrID
137 [137]: GETTABLE  R2 R2 K246   ; R2 := R2["MSI_HK_SKILLBAR1_3"]
138 [137]: SETTABLE  R1 K241 R2   ; R1["EXE"] := R2
139 [137]: SETTABLE  R1 K244 K169 ; R1["KEY1"] := 114
140 [137]: SETTABLE  R0 K3 R1     ; R0[2] := R1
141 [138]: NEWTABLE  R1 0 2       ; R1 := {}
142 [138]: GETGLOBAL R2 K242      ; R2 := MsgStrID
143 [138]: GETTABLE  R2 R2 K248   ; R2 := R2["MSI_HK_SKILLBAR1_4"]
144 [138]: SETTABLE  R1 K241 R2   ; R1["EXE"] := R2
145 [138]: SETTABLE  R1 K244 K171 ; R1["KEY1"] := 115
146 [138]: SETTABLE  R0 K247 R1   ; R0[3] := R1
147 [139]: NEWTABLE  R1 0 2       ; R1 := {}
148 [139]: GETGLOBAL R2 K242      ; R2 := MsgStrID
149 [139]: GETTABLE  R2 R2 K249   ; R2 := R2["MSI_HK_SKILLBAR1_5"]
150 [139]: SETTABLE  R1 K241 R2   ; R1["EXE"] := R2
151 [139]: SETTABLE  R1 K244 K173 ; R1["KEY1"] := 116
152 [139]: SETTABLE  R0 K5 R1     ; R0[4] := R1
153 [140]: NEWTABLE  R1 0 2       ; R1 := {}
154 [140]: GETGLOBAL R2 K242      ; R2 := MsgStrID
155 [140]: GETTABLE  R2 R2 K251   ; R2 := R2["MSI_HK_SKILLBAR1_6"]
156 [140]: SETTABLE  R1 K241 R2   ; R1["EXE"] := R2
157 [140]: SETTABLE  R1 K244 K175 ; R1["KEY1"] := 117
158 [140]: SETTABLE  R0 K250 R1   ; R0[5] := R1
159 [141]: NEWTABLE  R1 0 2       ; R1 := {}
160 [141]: GETGLOBAL R2 K242      ; R2 := MsgStrID
161 [141]: GETTABLE  R2 R2 K253   ; R2 := R2["MSI_HK_SKILLBAR1_7"]
162 [141]: SETTABLE  R1 K241 R2   ; R1["EXE"] := R2
163 [141]: SETTABLE  R1 K244 K177 ; R1["KEY1"] := 118
164 [141]: SETTABLE  R0 K252 R1   ; R0[6] := R1
165 [142]: NEWTABLE  R1 0 2       ; R1 := {}
166 [142]: GETGLOBAL R2 K242      ; R2 := MsgStrID
167 [142]: GETTABLE  R2 R2 K255   ; R2 := R2["MSI_HK_SKILLBAR1_8"]
168 [142]: SETTABLE  R1 K241 R2   ; R1["EXE"] := R2
169 [142]: SETTABLE  R1 K244 K179 ; R1["KEY1"] := 119
170 [142]: SETTABLE  R0 K254 R1   ; R0[7] := R1
171 [143]: NEWTABLE  R1 0 2       ; R1 := {}
172 [143]: GETGLOBAL R2 K242      ; R2 := MsgStrID
173 [143]: GETTABLE  R2 R2 K256   ; R2 := R2["MSI_HK_SKILLBAR1_9"]
174 [143]: SETTABLE  R1 K241 R2   ; R1["EXE"] := R2
175 [143]: SETTABLE  R1 K244 K181 ; R1["KEY1"] := 120
176 [143]: SETTABLE  R0 K7 R1     ; R0[8] := R1
177 [144]: NEWTABLE  R1 0 1       ; R1 := {}
178 [144]: GETGLOBAL R2 K242      ; R2 := MsgStrID
179 [144]: GETTABLE  R2 R2 K257   ; R2 := R2["MSI_HK_SKILLBAR2_1"]
180 [144]: SETTABLE  R1 K241 R2   ; R1["EXE"] := R2
181 [144]: SETTABLE  R0 K9 R1     ; R0[9] := R1
182 [145]: NEWTABLE  R1 0 1       ; R1 := {}
183 [145]: GETGLOBAL R2 K242      ; R2 := MsgStrID
184 [145]: GETTABLE  R2 R2 K259   ; R2 := R2["MSI_HK_SKILLBAR2_2"]
185 [145]: SETTABLE  R1 K241 R2   ; R1["EXE"] := R2
186 [145]: SETTABLE  R0 K258 R1   ; R0[10] := R1
187 [146]: NEWTABLE  R1 0 1       ; R1 := {}
188 [146]: GETGLOBAL R2 K242      ; R2 := MsgStrID
189 [146]: GETTABLE  R2 R2 K261   ; R2 := R2["MSI_HK_SKILLBAR2_3"]
190 [146]: SETTABLE  R1 K241 R2   ; R1["EXE"] := R2
191 [146]: SETTABLE  R0 K260 R1   ; R0[11] := R1
192 [147]: NEWTABLE  R1 0 1       ; R1 := {}
193 [147]: GETGLOBAL R2 K242      ; R2 := MsgStrID
194 [147]: LOADK     R3 K262      ; R3 := "MSI_HK_SKILLBAR2_4"
195 [147]: GETTABLE  R2 R2 R3     ; R2 := R2[R3]
196 [147]: SETTABLE  R1 K241 R2   ; R1["EXE"] := R2
197 [147]: SETTABLE  R0 K11 R1    ; R0[12] := R1
198 [148]: NEWTABLE  R1 0 1       ; R1 := {}
199 [148]: GETGLOBAL R2 K242      ; R2 := MsgStrID
200 [148]: LOADK     R3 K263      ; R3 := "MSI_HK_SKILLBAR2_5"
201 [148]: GETTABLE  R2 R2 R3     ; R2 := R2[R3]
202 [148]: SETTABLE  R1 K241 R2   ; R1["EXE"] := R2
203 [148]: SETTABLE  R0 K13 R1    ; R0[13] := R1
204 [149]: LOADK     R1 K264      ; R1 := 14
205 [149]: NEWTABLE  R2 0 1       ; R2 := {}
206 [149]: GETGLOBAL R3 K242      ; R3 := MsgStrID
207 [149]: LOADK     R4 K265      ; R4 := "MSI_HK_SKILLBAR2_6"
208 [149]: GETTABLE  R3 R3 R4     ; R3 := R3[R4]
209 [149]: SETTABLE  R2 K241 R3   ; R2["EXE"] := R3
210 [149]: SETTABLE  R0 R1 R2     ; R0[R1] := R2
211 [150]: LOADK     R1 K266      ; R1 := 15
212 [150]: NEWTABLE  R2 0 1       ; R2 := {}
213 [150]: GETGLOBAL R3 K242      ; R3 := MsgStrID
214 [150]: LOADK     R4 K267      ; R4 := "MSI_HK_SKILLBAR2_7"
215 [150]: GETTABLE  R3 R3 R4     ; R3 := R3[R4]
216 [150]: SETTABLE  R2 K241 R3   ; R2["EXE"] := R3
217 [150]: SETTABLE  R0 R1 R2     ; R0[R1] := R2
218 [151]: NEWTABLE  R1 0 1       ; R1 := {}
219 [151]: GETGLOBAL R2 K242      ; R2 := MsgStrID
220 [151]: LOADK     R3 K268      ; R3 := "MSI_HK_SKILLBAR2_8"
221 [151]: GETTABLE  R2 R2 R3     ; R2 := R2[R3]
222 [151]: SETTABLE  R1 K241 R2   ; R1["EXE"] := R2
223 [151]: SETTABLE  R0 K15 R1    ; R0[16] := R1
224 [152]: NEWTABLE  R1 0 1       ; R1 := {}
225 [152]: GETGLOBAL R2 K242      ; R2 := MsgStrID
226 [152]: LOADK     R3 K269      ; R3 := "MSI_HK_SKILLBAR2_9"
227 [152]: GETTABLE  R2 R2 R3     ; R2 := R2[R3]
228 [152]: SETTABLE  R1 K241 R2   ; R1["EXE"] := R2
229 [152]: SETTABLE  R0 K17 R1    ; R0[17] := R1
230 [153]: NEWTABLE  R1 0 1       ; R1 := {}
231 [153]: GETGLOBAL R2 K242      ; R2 := MsgStrID
232 [153]: LOADK     R3 K270      ; R3 := "MSI_HK_SKILLBAR3_1"
233 [153]: GETTABLE  R2 R2 R3     ; R2 := R2[R3]
234 [153]: SETTABLE  R1 K241 R2   ; R1["EXE"] := R2
235 [153]: SETTABLE  R0 K19 R1    ; R0[18] := R1
236 [154]: NEWTABLE  R1 0 1       ; R1 := {}
237 [154]: GETGLOBAL R2 K242      ; R2 := MsgStrID
238 [154]: LOADK     R3 K271      ; R3 := "MSI_HK_SKILLBAR3_2"
239 [154]: GETTABLE  R2 R2 R3     ; R2 := R2[R3]
240 [154]: SETTABLE  R1 K241 R2   ; R1["EXE"] := R2
241 [154]: SETTABLE  R0 K21 R1    ; R0[19] := R1
242 [155]: NEWTABLE  R1 0 1       ; R1 := {}
243 [155]: GETGLOBAL R2 K242      ; R2 := MsgStrID
244 [155]: LOADK     R3 K272      ; R3 := "MSI_HK_SKILLBAR3_3"
245 [155]: GETTABLE  R2 R2 R3     ; R2 := R2[R3]
246 [155]: SETTABLE  R1 K241 R2   ; R1["EXE"] := R2
247 [155]: SETTABLE  R0 K23 R1    ; R0[20] := R1
248 [156]: NEWTABLE  R1 0 1       ; R1 := {}
249 [156]: GETGLOBAL R2 K242      ; R2 := MsgStrID
250 [156]: LOADK     R3 K273      ; R3 := "MSI_HK_SKILLBAR3_4"
251 [156]: GETTABLE  R2 R2 R3     ; R2 := R2[R3]
252 [156]: SETTABLE  R1 K241 R2   ; R1["EXE"] := R2
253 [156]: SETTABLE  R0 K25 R1    ; R0[21] := R1
254 [157]: LOADK     R1 K274      ; R1 := 22
255 [157]: NEWTABLE  R2 0 1       ; R2 := {}
256 [157]: GETGLOBAL R3 K242      ; R3 := MsgStrID
257 [157]: LOADK     R4 K275      ; R4 := "MSI_HK_SKILLBAR3_5"
258 [157]: GETTABLE  R3 R3 R4     ; R3 := R3[R4]
259 [157]: SETTABLE  R2 K241 R3   ; R2["EXE"] := R3
260 [157]: SETTABLE  R0 R1 R2     ; R0[R1] := R2
261 [158]: LOADK     R1 K276      ; R1 := 23
262 [158]: NEWTABLE  R2 0 1       ; R2 := {}
263 [158]: GETGLOBAL R3 K242      ; R3 := MsgStrID
264 [158]: LOADK     R4 K277      ; R4 := "MSI_HK_SKILLBAR3_6"
265 [158]: GETTABLE  R3 R3 R4     ; R3 := R3[R4]
266 [158]: SETTABLE  R2 K241 R3   ; R2["EXE"] := R3
267 [158]: SETTABLE  R0 R1 R2     ; R0[R1] := R2
268 [159]: LOADK     R1 K278      ; R1 := 24
269 [159]: NEWTABLE  R2 0 1       ; R2 := {}
270 [159]: GETGLOBAL R3 K242      ; R3 := MsgStrID
271 [159]: LOADK     R4 K279      ; R4 := "MSI_HK_SKILLBAR3_7"
272 [159]: GETTABLE  R3 R3 R4     ; R3 := R3[R4]
273 [159]: SETTABLE  R2 K241 R3   ; R2["EXE"] := R3
274 [159]: SETTABLE  R0 R1 R2     ; R0[R1] := R2
275 [160]: NEWTABLE  R1 0 1       ; R1 := {}
276 [160]: GETGLOBAL R2 K242      ; R2 := MsgStrID
277 [160]: LOADK     R3 K280      ; R3 := "MSI_HK_SKILLBAR3_8"
278 [160]: GETTABLE  R2 R2 R3     ; R2 := R2[R3]
279 [160]: SETTABLE  R1 K241 R2   ; R1["EXE"] := R2
280 [160]: SETTABLE  R0 K27 R1    ; R0[25] := R1
281 [161]: LOADK     R1 K281      ; R1 := 26
282 [161]: NEWTABLE  R2 0 1       ; R2 := {}
283 [161]: GETGLOBAL R3 K242      ; R3 := MsgStrID
284 [161]: LOADK     R4 K282      ; R4 := "MSI_HK_SKILLBAR3_9"
285 [161]: GETTABLE  R3 R3 R4     ; R3 := R3[R4]
286 [161]: SETTABLE  R2 K241 R3   ; R2["EXE"] := R3
287 [161]: SETTABLE  R0 R1 R2     ; R0[R1] := R2
288 [162]: LOADK     R1 K283      ; R1 := 27
289 [162]: NEWTABLE  R2 0 1       ; R2 := {}
290 [162]: GETGLOBAL R3 K242      ; R3 := MsgStrID
291 [162]: LOADK     R4 K284      ; R4 := "MSI_HK_SKILLBAR4_1"
292 [162]: GETTABLE  R3 R3 R4     ; R3 := R3[R4]
293 [162]: SETTABLE  R2 K241 R3   ; R2["EXE"] := R3
294 [162]: SETTABLE  R0 R1 R2     ; R0[R1] := R2
295 [163]: LOADK     R1 K285      ; R1 := 28
296 [163]: NEWTABLE  R2 0 1       ; R2 := {}
297 [163]: GETGLOBAL R3 K242      ; R3 := MsgStrID
298 [163]: LOADK     R4 K286      ; R4 := "MSI_HK_SKILLBAR4_2"
299 [163]: GETTABLE  R3 R3 R4     ; R3 := R3[R4]
300 [163]: SETTABLE  R2 K241 R3   ; R2["EXE"] := R3
301 [163]: SETTABLE  R0 R1 R2     ; R0[R1] := R2
302 [164]: LOADK     R1 K287      ; R1 := 29
303 [164]: NEWTABLE  R2 0 1       ; R2 := {}
304 [164]: GETGLOBAL R3 K242      ; R3 := MsgStrID
305 [164]: LOADK     R4 K288      ; R4 := "MSI_HK_SKILLBAR4_3"
306 [164]: GETTABLE  R3 R3 R4     ; R3 := R3[R4]
307 [164]: SETTABLE  R2 K241 R3   ; R2["EXE"] := R3
308 [164]: SETTABLE  R0 R1 R2     ; R0[R1] := R2
309 [165]: LOADK     R1 K289      ; R1 := 30
310 [165]: NEWTABLE  R2 0 1       ; R2 := {}
311 [165]: GETGLOBAL R3 K242      ; R3 := MsgStrID
312 [165]: LOADK     R4 K290      ; R4 := "MSI_HK_SKILLBAR4_4"
313 [165]: GETTABLE  R3 R3 R4     ; R3 := R3[R4]
314 [165]: SETTABLE  R2 K241 R3   ; R2["EXE"] := R3
315 [165]: SETTABLE  R0 R1 R2     ; R0[R1] := R2
316 [166]: LOADK     R1 K291      ; R1 := 31
317 [166]: NEWTABLE  R2 0 1       ; R2 := {}
318 [166]: GETGLOBAL R3 K242      ; R3 := MsgStrID
319 [166]: LOADK     R4 K292      ; R4 := "MSI_HK_SKILLBAR4_5"
320 [166]: GETTABLE  R3 R3 R4     ; R3 := R3[R4]
321 [166]: SETTABLE  R2 K241 R3   ; R2["EXE"] := R3
322 [166]: SETTABLE  R0 R1 R2     ; R0[R1] := R2
323 [167]: NEWTABLE  R1 0 1       ; R1 := {}
324 [167]: GETGLOBAL R2 K242      ; R2 := MsgStrID
325 [167]: LOADK     R3 K293      ; R3 := "MSI_HK_SKILLBAR4_6"
326 [167]: GETTABLE  R2 R2 R3     ; R2 := R2[R3]
327 [167]: SETTABLE  R1 K241 R2   ; R1["EXE"] := R2
328 [167]: SETTABLE  R0 K29 R1    ; R0[32] := R1
329 [168]: NEWTABLE  R1 0 1       ; R1 := {}
330 [168]: GETGLOBAL R2 K242      ; R2 := MsgStrID
331 [168]: LOADK     R3 K294      ; R3 := "MSI_HK_SKILLBAR4_7"
332 [168]: GETTABLE  R2 R2 R3     ; R2 := R2[R3]
333 [168]: SETTABLE  R1 K241 R2   ; R1["EXE"] := R2
334 [168]: SETTABLE  R0 K31 R1    ; R0[33] := R1
335 [169]: NEWTABLE  R1 0 1       ; R1 := {}
336 [169]: GETGLOBAL R2 K242      ; R2 := MsgStrID
337 [169]: LOADK     R3 K295      ; R3 := "MSI_HK_SKILLBAR4_8"
338 [169]: GETTABLE  R2 R2 R3     ; R2 := R2[R3]
339 [169]: SETTABLE  R1 K241 R2   ; R1["EXE"] := R2
340 [169]: SETTABLE  R0 K33 R1    ; R0[34] := R1
341 [170]: NEWTABLE  R1 0 1       ; R1 := {}
342 [170]: GETGLOBAL R2 K242      ; R2 := MsgStrID
343 [170]: LOADK     R3 K296      ; R3 := "MSI_HK_SKILLBAR4_9"
344 [170]: GETTABLE  R2 R2 R3     ; R2 := R2[R3]
345 [170]: SETTABLE  R1 K241 R2   ; R1["EXE"] := R2
346 [170]: SETTABLE  R0 K35 R1    ; R0[35] := R1
347 [171]: SETGLOBAL R0 K239      ; HOTKEY_1 := R0
348 [173]: NEWTABLE  R0 0 0       ; R0 := {}
349 [174]: NEWTABLE  R1 0 2       ; R1 := {}
350 [174]: GETGLOBAL R2 K242      ; R2 := MsgStrID
351 [174]: LOADK     R3 K298      ; R3 := "MSI_HK_BASICINFOWND_MINI"
352 [174]: GETTABLE  R2 R2 R3     ; R2 := R2[R3]
353 [174]: SETTABLE  R1 K241 R2   ; R1["EXE"] := R2
354 [174]: SETTABLE  R1 K244 K121 ; R1["KEY1"] := 86
355 [174]: LOADK     R2 K299      ; R2 := "KEY2"
356 [174]: SETTABLE  R1 R2 K19    ; R1[R2] := 18
357 [174]: SETTABLE  R0 K240 R1   ; R0[0] := R1
358 [175]: NEWTABLE  R1 0 2       ; R1 := {}
359 [175]: GETGLOBAL R2 K242      ; R2 := MsgStrID
360 [175]: LOADK     R3 K300      ; R3 := "MSI_HK_EQUIPWND_ONOFF"
361 [175]: GETTABLE  R2 R2 R3     ; R2 := R2[R3]
362 [175]: SETTABLE  R1 K241 R2   ; R1["EXE"] := R2
363 [175]: SETTABLE  R1 K244 K111 ; R1["KEY1"] := 81
364 [175]: LOADK     R2 K299      ; R2 := "KEY2"
365 [175]: SETTABLE  R1 R2 K19    ; R1[R2] := 18
366 [175]: SETTABLE  R0 K1 R1     ; R0[1] := R1
367 [176]: NEWTABLE  R1 0 2       ; R1 := {}
368 [176]: GETGLOBAL R2 K242      ; R2 := MsgStrID
369 [176]: LOADK     R3 K301      ; R3 := "MSI_HK_SKILLWND_ONOFF"
370 [176]: GETTABLE  R2 R2 R3     ; R2 := R2[R3]
371 [176]: SETTABLE  R1 K241 R2   ; R1["EXE"] := R2
372 [176]: SETTABLE  R1 K244 K115 ; R1["KEY1"] := 83
373 [176]: LOADK     R2 K299      ; R2 := "KEY2"
374 [176]: SETTABLE  R1 R2 K19    ; R1[R2] := 18
375 [176]: SETTABLE  R0 K3 R1     ; R0[2] := R1
376 [177]: NEWTABLE  R1 0 2       ; R1 := {}
377 [177]: GETGLOBAL R2 K242      ; R2 := MsgStrID
378 [177]: LOADK     R3 K302      ; R3 := "MSI_HK_QUESTWND_ONOFF"
379 [177]: GETTABLE  R2 R2 R3     ; R2 := R2[R3]
380 [177]: SETTABLE  R1 K241 R2   ; R1["EXE"] := R2
381 [177]: SETTABLE  R1 K244 K119 ; R1["KEY1"] := 85
382 [177]: LOADK     R2 K299      ; R2 := "KEY2"
383 [177]: SETTABLE  R1 R2 K19    ; R1[R2] := 18
384 [177]: SETTABLE  R0 K247 R1   ; R0[3] := R1
385 [178]: NEWTABLE  R1 0 2       ; R1 := {}
386 [178]: GETGLOBAL R2 K242      ; R2 := MsgStrID
387 [178]: LOADK     R3 K303      ; R3 := "MSI_HK_FRIENDWND_ONOFF"
388 [178]: GETTABLE  R2 R2 R3     ; R2 := R2[R3]
389 [178]: SETTABLE  R1 K241 R2   ; R1["EXE"] := R2
390 [178]: SETTABLE  R1 K244 K93  ; R1["KEY1"] := 72
391 [178]: LOADK     R2 K299      ; R2 := "KEY2"
392 [178]: SETTABLE  R1 R2 K19    ; R1[R2] := 18
393 [178]: SETTABLE  R0 K5 R1     ; R0[4] := R1
394 [179]: NEWTABLE  R1 0 2       ; R1 := {}
395 [179]: GETGLOBAL R2 K242      ; R2 := MsgStrID
396 [179]: LOADK     R3 K304      ; R3 := "MSI_HK_PARTYWND_ONOFF"
397 [179]: GETTABLE  R2 R2 R3     ; R2 := R2[R3]
398 [179]: SETTABLE  R1 K241 R2   ; R1["EXE"] := R2
399 [179]: SETTABLE  R1 K244 K129 ; R1["KEY1"] := 90
400 [179]: LOADK     R2 K299      ; R2 := "KEY2"
401 [179]: SETTABLE  R1 R2 K19    ; R1[R2] := 18
402 [179]: SETTABLE  R0 K250 R1   ; R0[5] := R1
403 [180]: NEWTABLE  R1 0 2       ; R1 := {}
404 [180]: GETGLOBAL R2 K242      ; R2 := MsgStrID
405 [180]: LOADK     R3 K305      ; R3 := "MSI_HK_CHATWND_MAKE"
406 [180]: GETTABLE  R2 R2 R3     ; R2 := R2[R3]
407 [180]: SETTABLE  R1 K241 R2   ; R1["EXE"] := R2
408 [180]: SETTABLE  R1 K244 K83  ; R1["KEY1"] := 67
409 [180]: LOADK     R2 K299      ; R2 := "KEY2"
410 [180]: SETTABLE  R1 R2 K19    ; R1[R2] := 18
411 [180]: SETTABLE  R0 K252 R1   ; R0[6] := R1
412 [181]: NEWTABLE  R1 0 2       ; R1 := {}
413 [181]: GETGLOBAL R2 K242      ; R2 := MsgStrID
414 [181]: LOADK     R3 K306      ; R3 := "MSI_HK_CARTWND_ONOFF"
415 [181]: GETTABLE  R2 R2 R3     ; R2 := R2[R3]
416 [181]: SETTABLE  R1 K241 R2   ; R1["EXE"] := R2
417 [181]: SETTABLE  R1 K244 K123 ; R1["KEY1"] := 87
418 [181]: LOADK     R2 K299      ; R2 := "KEY2"
419 [181]: SETTABLE  R1 R2 K19    ; R1[R2] := 18
420 [181]: SETTABLE  R0 K254 R1   ; R0[7] := R1
421 [182]: NEWTABLE  R1 0 2       ; R1 := {}
422 [182]: GETGLOBAL R2 K242      ; R2 := MsgStrID
423 [182]: LOADK     R3 K307      ; R3 := "MSI_HK_MAPWND_ONOFF"
424 [182]: GETTABLE  R2 R2 R3     ; R2 := R2[R3]
425 [182]: SETTABLE  R1 K241 R2   ; R1["EXE"] := R2
426 [182]: SETTABLE  R1 K244 K229 ; R1["KEY1"] := 192
427 [182]: LOADK     R2 K299      ; R2 := "KEY2"
428 [182]: SETTABLE  R1 R2 K17    ; R1[R2] := 17
429 [182]: SETTABLE  R0 K7 R1     ; R0[8] := R1
430 [183]: NEWTABLE  R1 0 2       ; R1 := {}
431 [183]: GETGLOBAL R2 K242      ; R2 := MsgStrID
432 [183]: LOADK     R3 K308      ; R3 := "MSI_HK_ITEMWND_ONOFF"
433 [183]: GETTABLE  R2 R2 R3     ; R2 := R2[R3]
434 [183]: SETTABLE  R1 K241 R2   ; R1["EXE"] := R2
435 [183]: SETTABLE  R1 K244 K87  ; R1["KEY1"] := 69
436 [183]: LOADK     R2 K299      ; R2 := "KEY2"
437 [183]: SETTABLE  R1 R2 K19    ; R1[R2] := 18
438 [183]: SETTABLE  R0 K9 R1     ; R0[9] := R1
439 [184]: NEWTABLE  R1 0 2       ; R1 := {}
440 [184]: GETGLOBAL R2 K242      ; R2 := MsgStrID
441 [184]: LOADK     R3 K309      ; R3 := "MSI_HK_GUILDWND_ONOFF"
442 [184]: GETTABLE  R2 R2 R3     ; R2 := R2[R3]
443 [184]: SETTABLE  R1 K241 R2   ; R1["EXE"] := R2
444 [184]: SETTABLE  R1 K244 K91  ; R1["KEY1"] := 71
445 [184]: LOADK     R2 K299      ; R2 := "KEY2"
446 [184]: SETTABLE  R1 R2 K19    ; R1[R2] := 18
447 [184]: SETTABLE  R0 K258 R1   ; R0[10] := R1
448 [185]: NEWTABLE  R1 0 2       ; R1 := {}
449 [185]: GETGLOBAL R2 K242      ; R2 := MsgStrID
450 [185]: LOADK     R3 K310      ; R3 := "MSI_HK_EMOTIONWND_ONOFF"
451 [185]: GETTABLE  R2 R2 R3     ; R2 := R2[R3]
452 [185]: SETTABLE  R1 K241 R2   ; R1["EXE"] := R2
453 [185]: SETTABLE  R1 K244 K101 ; R1["KEY1"] := 76
454 [185]: LOADK     R2 K299      ; R2 := "KEY2"
455 [185]: SETTABLE  R1 R2 K19    ; R1[R2] := 18
456 [185]: SETTABLE  R0 K260 R1   ; R0[11] := R1
457 [186]: NEWTABLE  R1 0 2       ; R1 := {}
458 [186]: GETGLOBAL R2 K242      ; R2 := MsgStrID
459 [186]: LOADK     R3 K311      ; R3 := "MSI_HK_SITORSTAND"
460 [186]: GETTABLE  R2 R2 R3     ; R2 := R2[R3]
461 [186]: SETTABLE  R1 K241 R2   ; R1["EXE"] := R2
462 [186]: SETTABLE  R1 K244 K53  ; R1["KEY1"] := 45
463 [186]: SETTABLE  R0 K11 R1    ; R0[12] := R1
464 [187]: NEWTABLE  R1 0 2       ; R1 := {}
465 [187]: GETGLOBAL R2 K242      ; R2 := MsgStrID
466 [187]: LOADK     R3 K312      ; R3 := "MSI_HK_MINIMAP_ONOFF"
467 [187]: GETTABLE  R2 R2 R3     ; R2 := R2[R3]
468 [187]: SETTABLE  R1 K241 R2   ; R1["EXE"] := R2
469 [187]: SETTABLE  R1 K244 K9   ; R1["KEY1"] := 9
470 [187]: LOADK     R2 K299      ; R2 := "KEY2"
471 [187]: SETTABLE  R1 R2 K17    ; R1[R2] := 17
472 [187]: SETTABLE  R0 K13 R1    ; R0[13] := R1
473 [188]: LOADK     R1 K264      ; R1 := 14
474 [188]: NEWTABLE  R2 0 2       ; R2 := {}
475 [188]: GETGLOBAL R3 K242      ; R3 := MsgStrID
476 [188]: LOADK     R4 K313      ; R4 := "MSI_HK_MACROWND_ONOFF"
477 [188]: GETTABLE  R3 R3 R4     ; R3 := R3[R4]
478 [188]: SETTABLE  R2 K241 R3   ; R2["EXE"] := R3
479 [188]: SETTABLE  R2 K244 K103 ; R2["KEY1"] := 77
480 [188]: LOADK     R3 K299      ; R3 := "KEY2"
481 [188]: SETTABLE  R2 R3 K19    ; R2[R3] := 18
482 [188]: SETTABLE  R0 R1 R2     ; R0[R1] := R2
483 [189]: LOADK     R1 K266      ; R1 := 15
484 [189]: NEWTABLE  R2 0 2       ; R2 := {}
485 [189]: GETGLOBAL R3 K242      ; R3 := MsgStrID
486 [189]: LOADK     R4 K314      ; R4 := "MSI_HK_EXEWND_ONOFF"
487 [189]: GETTABLE  R3 R3 R4     ; R3 := R3[R4]
488 [189]: SETTABLE  R2 K241 R3   ; R2["EXE"] := R3
489 [189]: SETTABLE  R2 K244 K127 ; R2["KEY1"] := 89
490 [189]: LOADK     R3 K299      ; R3 := "KEY2"
491 [189]: SETTABLE  R2 R3 K19    ; R2[R3] := 18
492 [189]: SETTABLE  R0 R1 R2     ; R0[R1] := R2
493 [190]: NEWTABLE  R1 0 2       ; R1 := {}
494 [190]: GETGLOBAL R2 K242      ; R2 := MsgStrID
495 [190]: LOADK     R3 K315      ; R3 := "MSI_HK_ALLWND_OFF"
496 [190]: GETTABLE  R2 R2 R3     ; R2 := R2[R3]
497 [190]: SETTABLE  R1 K241 R2   ; R1["EXE"] := R2
498 [190]: SETTABLE  R1 K244 K185 ; R1["KEY1"] := 122
499 [190]: SETTABLE  R0 K15 R1    ; R0[16] := R1
500 [191]: NEWTABLE  R1 0 2       ; R1 := {}
501 [191]: GETGLOBAL R2 K242      ; R2 := MsgStrID
502 [191]: LOADK     R3 K316      ; R3 := "MSI_HK_SKILLBAR_ONOFF"
503 [191]: GETTABLE  R2 R2 R3     ; R2 := R2[R3]
504 [191]: SETTABLE  R1 K241 R2   ; R1["EXE"] := R2
505 [191]: SETTABLE  R1 K244 K187 ; R1["KEY1"] := 123
506 [191]: SETTABLE  R0 K17 R1    ; R0[17] := R1
507 [192]: NEWTABLE  R1 0 2       ; R1 := {}
508 [192]: GETGLOBAL R2 K242      ; R2 := MsgStrID
509 [192]: LOADK     R3 K317      ; R3 := "MSI_HK_CHATWND_ONOFF"
510 [192]: GETTABLE  R2 R2 R3     ; R2 := R2[R3]
511 [192]: SETTABLE  R1 K241 R2   ; R1["EXE"] := R2
512 [192]: SETTABLE  R1 K244 K183 ; R1["KEY1"] := 121
513 [192]: LOADK     R2 K299      ; R2 := "KEY2"
514 [192]: SETTABLE  R1 R2 K19    ; R1[R2] := 18
515 [192]: SETTABLE  R0 K19 R1    ; R0[18] := R1
516 [193]: NEWTABLE  R1 0 2       ; R1 := {}
517 [193]: GETGLOBAL R2 K242      ; R2 := MsgStrID
518 [193]: LOADK     R3 K318      ; R3 := "MSI_HK_CHATWND_ZOOM"
519 [193]: GETTABLE  R2 R2 R3     ; R2 := R2[R3]
520 [193]: SETTABLE  R1 K241 R2   ; R1["EXE"] := R2
521 [193]: SETTABLE  R1 K244 K183 ; R1["KEY1"] := 121
522 [193]: SETTABLE  R0 K21 R1    ; R0[19] := R1
523 [194]: NEWTABLE  R1 0 2       ; R1 := {}
524 [194]: GETGLOBAL R2 K242      ; R2 := MsgStrID
525 [194]: LOADK     R3 K319      ; R3 := "MSI_HK_GAGE_ONOFF"
526 [194]: GETTABLE  R2 R2 R3     ; R2 := R2[R3]
527 [194]: SETTABLE  R1 K241 R2   ; R1["EXE"] := R2
528 [194]: SETTABLE  R1 K244 K35  ; R1["KEY1"] := 35
529 [194]: LOADK     R2 K299      ; R2 := "KEY2"
530 [194]: SETTABLE  R1 R2 K19    ; R1[R2] := 18
531 [194]: SETTABLE  R0 K23 R1    ; R0[20] := R1
532 [195]: NEWTABLE  R1 0 2       ; R1 := {}
533 [195]: GETGLOBAL R2 K242      ; R2 := MsgStrID
534 [195]: LOADK     R3 K320      ; R3 := "MSI_HK_SNAPSHOT"
535 [195]: GETTABLE  R2 R2 R3     ; R2 := R2[R3]
536 [195]: SETTABLE  R1 K241 R2   ; R1["EXE"] := R2
537 [195]: SETTABLE  R1 K244 K51  ; R1["KEY1"] := 44
538 [195]: SETTABLE  R0 K25 R1    ; R0[21] := R1
539 [196]: LOADK     R1 K274      ; R1 := 22
540 [196]: NEWTABLE  R2 0 2       ; R2 := {}
541 [196]: GETGLOBAL R3 K242      ; R3 := MsgStrID
542 [196]: LOADK     R4 K321      ; R4 := "MSI_HK_MEMORIALWND_ONOFF"
543 [196]: GETTABLE  R3 R3 R4     ; R3 := R3[R4]
544 [196]: SETTABLE  R2 K241 R3   ; R2["EXE"] := R3
545 [196]: SETTABLE  R2 K244 K81  ; R2["KEY1"] := 66
546 [196]: LOADK     R3 K299      ; R3 := "KEY2"
547 [196]: SETTABLE  R2 R3 K19    ; R2[R3] := 18
548 [196]: SETTABLE  R0 R1 R2     ; R0[R1] := R2
549 [197]: LOADK     R1 K276      ; R1 := 23
550 [197]: NEWTABLE  R2 0 2       ; R2 := {}
551 [197]: GETGLOBAL R3 K242      ; R3 := MsgStrID
552 [197]: LOADK     R4 K322      ; R4 := "MSI_HK_PETWND_ONOFF"
553 [197]: GETTABLE  R3 R3 R4     ; R3 := R3[R4]
554 [197]: SETTABLE  R2 K241 R3   ; R2["EXE"] := R3
555 [197]: SETTABLE  R2 K244 K97  ; R2["KEY1"] := 74
556 [197]: LOADK     R3 K299      ; R3 := "KEY2"
557 [197]: SETTABLE  R2 R3 K19    ; R2[R3] := 18
558 [197]: SETTABLE  R0 R1 R2     ; R0[R1] := R2
559 [198]: LOADK     R1 K278      ; R1 := 24
560 [198]: NEWTABLE  R2 0 2       ; R2 := {}
561 [198]: GETGLOBAL R3 K242      ; R3 := MsgStrID
562 [198]: LOADK     R4 K323      ; R4 := "MSI_HK_HOMUNWND_ONOFF"
563 [198]: GETTABLE  R3 R3 R4     ; R3 := R3[R4]
564 [198]: SETTABLE  R2 K241 R3   ; R2["EXE"] := R3
565 [198]: SETTABLE  R2 K244 K113 ; R2["KEY1"] := 82
566 [198]: LOADK     R3 K299      ; R3 := "KEY2"
567 [198]: SETTABLE  R2 R3 K19    ; R2[R3] := 18
568 [198]: SETTABLE  R0 R1 R2     ; R0[R1] := R2
569 [199]: NEWTABLE  R1 0 2       ; R1 := {}
570 [199]: GETGLOBAL R2 K242      ; R2 := MsgStrID
571 [199]: LOADK     R3 K324      ; R3 := "MSI_HK_MERWND_ONOFF"
572 [199]: GETTABLE  R2 R2 R3     ; R2 := R2[R3]
573 [199]: SETTABLE  R1 K241 R2   ; R1["EXE"] := R2
574 [199]: SETTABLE  R1 K244 K113 ; R1["KEY1"] := 82
575 [199]: LOADK     R2 K299      ; R2 := "KEY2"
576 [199]: SETTABLE  R1 R2 K17    ; R1[R2] := 17
577 [199]: SETTABLE  R0 K27 R1    ; R0[25] := R1
578 [200]: LOADK     R1 K281      ; R1 := 26
579 [200]: NEWTABLE  R2 0 2       ; R2 := {}
580 [200]: GETGLOBAL R3 K242      ; R3 := MsgStrID
581 [200]: LOADK     R4 K325      ; R4 := "MSI_HK_HOMUN_FOLLOW"
582 [200]: GETTABLE  R3 R3 R4     ; R3 := R3[R4]
583 [200]: SETTABLE  R2 K241 R3   ; R2["EXE"] := R3
584 [200]: SETTABLE  R2 K244 K117 ; R2["KEY1"] := 84
585 [200]: LOADK     R3 K299      ; R3 := "KEY2"
586 [200]: SETTABLE  R2 R3 K19    ; R2[R3] := 18
587 [200]: SETTABLE  R0 R1 R2     ; R0[R1] := R2
588 [201]: LOADK     R1 K283      ; R1 := 27
589 [201]: NEWTABLE  R2 0 2       ; R2 := {}
590 [201]: GETGLOBAL R3 K242      ; R3 := MsgStrID
591 [201]: LOADK     R4 K326      ; R4 := "MSI_HK_MER_FOLLOW"
592 [201]: GETTABLE  R3 R3 R4     ; R3 := R3[R4]
593 [201]: SETTABLE  R2 K241 R3   ; R2["EXE"] := R3
594 [201]: SETTABLE  R2 K244 K117 ; R2["KEY1"] := 84
595 [201]: LOADK     R3 K299      ; R3 := "KEY2"
596 [201]: SETTABLE  R2 R3 K17    ; R2[R3] := 17
597 [201]: SETTABLE  R0 R1 R2     ; R0[R1] := R2
598 [202]: LOADK     R1 K285      ; R1 := 28
599 [202]: NEWTABLE  R2 0 1       ; R2 := {}
600 [202]: GETGLOBAL R3 K242      ; R3 := MsgStrID
601 [202]: LOADK     R4 K327      ; R4 := "MSI_HK_FRIEND_OPTIONWND"
602 [202]: GETTABLE  R3 R3 R4     ; R3 := R3[R4]
603 [202]: SETTABLE  R2 K241 R3   ; R2["EXE"] := R3
604 [202]: SETTABLE  R0 R1 R2     ; R0[R1] := R2
605 [203]: LOADK     R1 K287      ; R1 := 29
606 [203]: NEWTABLE  R2 0 1       ; R2 := {}
607 [203]: GETGLOBAL R3 K242      ; R3 := MsgStrID
608 [203]: LOADK     R4 K328      ; R4 := "MSI_HK_PARTY_OPTIONWND"
609 [203]: GETTABLE  R3 R3 R4     ; R3 := R3[R4]
610 [203]: SETTABLE  R2 K241 R3   ; R2["EXE"] := R3
611 [203]: SETTABLE  R0 R1 R2     ; R0[R1] := R2
612 [204]: LOADK     R1 K289      ; R1 := 30
613 [204]: NEWTABLE  R2 0 1       ; R2 := {}
614 [204]: GETGLOBAL R3 K242      ; R3 := MsgStrID
615 [204]: LOADK     R4 K329      ; R4 := "MSI_HK_BATTLEFIELDWND"
616 [204]: GETTABLE  R3 R3 R4     ; R3 := R3[R4]
617 [204]: SETTABLE  R2 K241 R3   ; R2["EXE"] := R3
618 [204]: SETTABLE  R0 R1 R2     ; R0[R1] := R2
619 [205]: LOADK     R1 K291      ; R1 := 31
620 [205]: NEWTABLE  R2 0 2       ; R2 := {}
621 [205]: GETGLOBAL R3 K242      ; R3 := MsgStrID
622 [205]: LOADK     R4 K330      ; R4 := "MSI_HK_CHATMODE_ONOFF"
623 [205]: GETTABLE  R3 R3 R4     ; R3 := R3[R4]
624 [205]: SETTABLE  R2 K241 R3   ; R2["EXE"] := R3
625 [205]: SETTABLE  R2 K244 K13  ; R2["KEY1"] := 13
626 [205]: SETTABLE  R0 R1 R2     ; R0[R1] := R2
627 [206]: NEWTABLE  R1 0 2       ; R1 := {}
628 [206]: GETGLOBAL R2 K242      ; R2 := MsgStrID
629 [206]: LOADK     R3 K331      ; R3 := "MSI_HK_BASICINFOWND_BTN_ONOFF"
630 [206]: GETTABLE  R2 R2 R3     ; R2 := R2[R3]
631 [206]: SETTABLE  R1 K241 R2   ; R1["EXE"] := R2
632 [206]: SETTABLE  R1 K244 K229 ; R1["KEY1"] := 192
633 [206]: LOADK     R2 K299      ; R2 := "KEY2"
634 [206]: SETTABLE  R1 R2 K19    ; R1[R2] := 18
635 [206]: SETTABLE  R0 K29 R1    ; R0[32] := R1
636 [207]: NEWTABLE  R1 0 1       ; R1 := {}
637 [207]: GETGLOBAL R2 K242      ; R2 := MsgStrID
638 [207]: LOADK     R3 K332      ; R3 := "MSI_HK_PARTY_RECRUIT"
639 [207]: GETTABLE  R2 R2 R3     ; R2 := R2[R3]
640 [207]: SETTABLE  R1 K241 R2   ; R1["EXE"] := R2
641 [207]: SETTABLE  R0 K31 R1    ; R0[33] := R1
642 [208]: NEWTABLE  R1 0 1       ; R1 := {}
643 [208]: GETGLOBAL R2 K242      ; R2 := MsgStrID
644 [208]: LOADK     R3 K333      ; R3 := "MSI_HK_PARTY_BOOKING_LIST"
645 [208]: GETTABLE  R2 R2 R3     ; R2 := R2[R3]
646 [208]: SETTABLE  R1 K241 R2   ; R1["EXE"] := R2
647 [208]: SETTABLE  R0 K33 R1    ; R0[34] := R1
648 [209]: NEWTABLE  R1 0 2       ; R1 := {}
649 [209]: GETGLOBAL R2 K242      ; R2 := MsgStrID
650 [209]: LOADK     R3 K334      ; R3 := "MSI_HK_GROUND_CURSOR_ONOFF"
651 [209]: GETTABLE  R2 R2 R3     ; R2 := R2[R3]
652 [209]: SETTABLE  R1 K241 R2   ; R1["EXE"] := R2
653 [209]: SETTABLE  R1 K244 K37  ; R1["KEY1"] := 36
654 [209]: LOADK     R2 K299      ; R2 := "KEY2"
655 [209]: SETTABLE  R1 R2 K19    ; R1[R2] := 18
656 [209]: SETTABLE  R0 K35 R1    ; R0[35] := R1
657 [210]: NEWTABLE  R1 0 1       ; R1 := {}
658 [210]: GETGLOBAL R2 K242      ; R2 := MsgStrID
659 [210]: LOADK     R3 K335      ; R3 := "MSI_HK_EXMACRO_SETUPWND"
660 [210]: GETTABLE  R2 R2 R3     ; R2 := R2[R3]
661 [210]: SETTABLE  R1 K241 R2   ; R1["EXE"] := R2
662 [210]: SETTABLE  R0 K37 R1    ; R0[36] := R1
663 [211]: NEWTABLE  R1 0 1       ; R1 := {}
664 [211]: GETGLOBAL R2 K242      ; R2 := MsgStrID
665 [211]: LOADK     R3 K336      ; R3 := "MSI_HK_CASHSHOPWND"
666 [211]: GETTABLE  R2 R2 R3     ; R2 := R2[R3]
667 [211]: SETTABLE  R1 K241 R2   ; R1["EXE"] := R2
668 [211]: SETTABLE  R0 K39 R1    ; R0[37] := R1
669 [212]: SETGLOBAL R0 K297      ; HOTKEY_2 := R0
670 [214]: NEWTABLE  R0 0 0       ; R0 := {}
671 [215]: NEWTABLE  R1 0 2       ; R1 := {}
672 [215]: GETGLOBAL R2 K242      ; R2 := MsgStrID
673 [215]: LOADK     R3 K338      ; R3 := "MSI_HK_MACRO_1"
674 [215]: GETTABLE  R2 R2 R3     ; R2 := R2[R3]
675 [215]: SETTABLE  R1 K241 R2   ; R1["EXE"] := R2
676 [215]: SETTABLE  R1 K244 K61  ; R1["KEY1"] := 49
677 [215]: LOADK     R2 K299      ; R2 := "KEY2"
678 [215]: SETTABLE  R1 R2 K19    ; R1[R2] := 18
679 [215]: SETTABLE  R0 K240 R1   ; R0[0] := R1
680 [216]: NEWTABLE  R1 0 2       ; R1 := {}
681 [216]: GETGLOBAL R2 K242      ; R2 := MsgStrID
682 [216]: LOADK     R3 K339      ; R3 := "MSI_HK_MACRO_2"
683 [216]: GETTABLE  R2 R2 R3     ; R2 := R2[R3]
684 [216]: SETTABLE  R1 K241 R2   ; R1["EXE"] := R2
685 [216]: SETTABLE  R1 K244 K63  ; R1["KEY1"] := 50
686 [216]: LOADK     R2 K299      ; R2 := "KEY2"
687 [216]: SETTABLE  R1 R2 K19    ; R1[R2] := 18
688 [216]: SETTABLE  R0 K1 R1     ; R0[1] := R1
689 [217]: NEWTABLE  R1 0 2       ; R1 := {}
690 [217]: GETGLOBAL R2 K242      ; R2 := MsgStrID
691 [217]: LOADK     R3 K340      ; R3 := "MSI_HK_MACRO_3"
692 [217]: GETTABLE  R2 R2 R3     ; R2 := R2[R3]
693 [217]: SETTABLE  R1 K241 R2   ; R1["EXE"] := R2
694 [217]: SETTABLE  R1 K244 K65  ; R1["KEY1"] := 51
695 [217]: LOADK     R2 K299      ; R2 := "KEY2"
696 [217]: SETTABLE  R1 R2 K19    ; R1[R2] := 18
697 [217]: SETTABLE  R0 K3 R1     ; R0[2] := R1
698 [218]: NEWTABLE  R1 0 2       ; R1 := {}
699 [218]: GETGLOBAL R2 K242      ; R2 := MsgStrID
700 [218]: LOADK     R3 K341      ; R3 := "MSI_HK_MACRO_4"
701 [218]: GETTABLE  R2 R2 R3     ; R2 := R2[R3]
702 [218]: SETTABLE  R1 K241 R2   ; R1["EXE"] := R2
703 [218]: SETTABLE  R1 K244 K67  ; R1["KEY1"] := 52
704 [218]: LOADK     R2 K299      ; R2 := "KEY2"
705 [218]: SETTABLE  R1 R2 K19    ; R1[R2] := 18
706 [218]: SETTABLE  R0 K247 R1   ; R0[3] := R1
707 [219]: NEWTABLE  R1 0 2       ; R1 := {}
708 [219]: GETGLOBAL R2 K242      ; R2 := MsgStrID
709 [219]: LOADK     R3 K342      ; R3 := "MSI_HK_MACRO_5"
710 [219]: GETTABLE  R2 R2 R3     ; R2 := R2[R3]
711 [219]: SETTABLE  R1 K241 R2   ; R1["EXE"] := R2
712 [219]: SETTABLE  R1 K244 K69  ; R1["KEY1"] := 53
713 [219]: LOADK     R2 K299      ; R2 := "KEY2"
714 [219]: SETTABLE  R1 R2 K19    ; R1[R2] := 18
715 [219]: SETTABLE  R0 K5 R1     ; R0[4] := R1
716 [220]: NEWTABLE  R1 0 2       ; R1 := {}
717 [220]: GETGLOBAL R2 K242      ; R2 := MsgStrID
718 [220]: LOADK     R3 K343      ; R3 := "MSI_HK_MACRO_6"
719 [220]: GETTABLE  R2 R2 R3     ; R2 := R2[R3]
720 [220]: SETTABLE  R1 K241 R2   ; R1["EXE"] := R2
721 [220]: SETTABLE  R1 K244 K71  ; R1["KEY1"] := 54
722 [220]: LOADK     R2 K299      ; R2 := "KEY2"
723 [220]: SETTABLE  R1 R2 K19    ; R1[R2] := 18
724 [220]: SETTABLE  R0 K250 R1   ; R0[5] := R1
725 [221]: NEWTABLE  R1 0 2       ; R1 := {}
726 [221]: GETGLOBAL R2 K242      ; R2 := MsgStrID
727 [221]: LOADK     R3 K344      ; R3 := "MSI_HK_MACRO_7"
728 [221]: GETTABLE  R2 R2 R3     ; R2 := R2[R3]
729 [221]: SETTABLE  R1 K241 R2   ; R1["EXE"] := R2
730 [221]: SETTABLE  R1 K244 K73  ; R1["KEY1"] := 55
731 [221]: LOADK     R2 K299      ; R2 := "KEY2"
732 [221]: SETTABLE  R1 R2 K19    ; R1[R2] := 18
733 [221]: SETTABLE  R0 K252 R1   ; R0[6] := R1
734 [222]: NEWTABLE  R1 0 2       ; R1 := {}
735 [222]: GETGLOBAL R2 K242      ; R2 := MsgStrID
736 [222]: LOADK     R3 K345      ; R3 := "MSI_HK_MACRO_8"
737 [222]: GETTABLE  R2 R2 R3     ; R2 := R2[R3]
738 [222]: SETTABLE  R1 K241 R2   ; R1["EXE"] := R2
739 [222]: SETTABLE  R1 K244 K75  ; R1["KEY1"] := 56
740 [222]: LOADK     R2 K299      ; R2 := "KEY2"
741 [222]: SETTABLE  R1 R2 K19    ; R1[R2] := 18
742 [222]: SETTABLE  R0 K254 R1   ; R0[7] := R1
743 [223]: NEWTABLE  R1 0 2       ; R1 := {}
744 [223]: GETGLOBAL R2 K242      ; R2 := MsgStrID
745 [223]: LOADK     R3 K346      ; R3 := "MSI_HK_MACRO_9"
746 [223]: GETTABLE  R2 R2 R3     ; R2 := R2[R3]
747 [223]: SETTABLE  R1 K241 R2   ; R1["EXE"] := R2
748 [223]: SETTABLE  R1 K244 K77  ; R1["KEY1"] := 57
749 [223]: LOADK     R2 K299      ; R2 := "KEY2"
750 [223]: SETTABLE  R1 R2 K19    ; R1[R2] := 18
751 [223]: SETTABLE  R0 K7 R1     ; R0[8] := R1
752 [224]: NEWTABLE  R1 0 2       ; R1 := {}
753 [224]: GETGLOBAL R2 K242      ; R2 := MsgStrID
754 [224]: LOADK     R3 K347      ; R3 := "MSI_HK_MACRO_10"
755 [224]: GETTABLE  R2 R2 R3     ; R2 := R2[R3]
756 [224]: SETTABLE  R1 K241 R2   ; R1["EXE"] := R2
757 [224]: SETTABLE  R1 K244 K59  ; R1["KEY1"] := 48
758 [224]: LOADK     R2 K299      ; R2 := "KEY2"
759 [224]: SETTABLE  R1 R2 K19    ; R1[R2] := 18
760 [224]: SETTABLE  R0 K9 R1     ; R0[9] := R1
761 [225]: NEWTABLE  R1 0 2       ; R1 := {}
762 [225]: GETGLOBAL R2 K242      ; R2 := MsgStrID
763 [225]: LOADK     R3 K348      ; R3 := "MSI_HK_FLAG_1"
764 [225]: GETTABLE  R2 R2 R3     ; R2 := R2[R3]
765 [225]: SETTABLE  R1 K241 R2   ; R1["EXE"] := R2
766 [225]: SETTABLE  R1 K244 K61  ; R1["KEY1"] := 49
767 [225]: LOADK     R2 K299      ; R2 := "KEY2"
768 [225]: SETTABLE  R1 R2 K17    ; R1[R2] := 17
769 [225]: SETTABLE  R0 K258 R1   ; R0[10] := R1
770 [226]: NEWTABLE  R1 0 2       ; R1 := {}
771 [226]: GETGLOBAL R2 K242      ; R2 := MsgStrID
772 [226]: LOADK     R3 K349      ; R3 := "MSI_HK_FLAG_2"
773 [226]: GETTABLE  R2 R2 R3     ; R2 := R2[R3]
774 [226]: SETTABLE  R1 K241 R2   ; R1["EXE"] := R2
775 [226]: SETTABLE  R1 K244 K63  ; R1["KEY1"] := 50
776 [226]: LOADK     R2 K299      ; R2 := "KEY2"
777 [226]: SETTABLE  R1 R2 K17    ; R1[R2] := 17
778 [226]: SETTABLE  R0 K260 R1   ; R0[11] := R1
779 [227]: NEWTABLE  R1 0 2       ; R1 := {}
780 [227]: GETGLOBAL R2 K242      ; R2 := MsgStrID
781 [227]: LOADK     R3 K350      ; R3 := "MSI_HK_FLAG_3"
782 [227]: GETTABLE  R2 R2 R3     ; R2 := R2[R3]
783 [227]: SETTABLE  R1 K241 R2   ; R1["EXE"] := R2
784 [227]: SETTABLE  R1 K244 K65  ; R1["KEY1"] := 51
785 [227]: LOADK     R2 K299      ; R2 := "KEY2"
786 [227]: SETTABLE  R1 R2 K17    ; R1[R2] := 17
787 [227]: SETTABLE  R0 K11 R1    ; R0[12] := R1
788 [228]: NEWTABLE  R1 0 2       ; R1 := {}
789 [228]: GETGLOBAL R2 K242      ; R2 := MsgStrID
790 [228]: LOADK     R3 K351      ; R3 := "MSI_HK_FLAG_4"
791 [228]: GETTABLE  R2 R2 R3     ; R2 := R2[R3]
792 [228]: SETTABLE  R1 K241 R2   ; R1["EXE"] := R2
793 [228]: SETTABLE  R1 K244 K67  ; R1["KEY1"] := 52
794 [228]: LOADK     R2 K299      ; R2 := "KEY2"
795 [228]: SETTABLE  R1 R2 K17    ; R1[R2] := 17
796 [228]: SETTABLE  R0 K13 R1    ; R0[13] := R1
797 [229]: LOADK     R1 K264      ; R1 := 14
798 [229]: NEWTABLE  R2 0 2       ; R2 := {}
799 [229]: GETGLOBAL R3 K242      ; R3 := MsgStrID
800 [229]: LOADK     R4 K352      ; R4 := "MSI_HK_FLAG_5"
801 [229]: GETTABLE  R3 R3 R4     ; R3 := R3[R4]
802 [229]: SETTABLE  R2 K241 R3   ; R2["EXE"] := R3
803 [229]: SETTABLE  R2 K244 K69  ; R2["KEY1"] := 53
804 [229]: LOADK     R3 K299      ; R3 := "KEY2"
805 [229]: SETTABLE  R2 R3 K17    ; R2[R3] := 17
806 [229]: SETTABLE  R0 R1 R2     ; R0[R1] := R2
807 [230]: LOADK     R1 K266      ; R1 := 15
808 [230]: NEWTABLE  R2 0 2       ; R2 := {}
809 [230]: GETGLOBAL R3 K242      ; R3 := MsgStrID
810 [230]: LOADK     R4 K353      ; R4 := "MSI_HK_FLAG_6"
811 [230]: GETTABLE  R3 R3 R4     ; R3 := R3[R4]
812 [230]: SETTABLE  R2 K241 R3   ; R2["EXE"] := R3
813 [230]: SETTABLE  R2 K244 K71  ; R2["KEY1"] := 54
814 [230]: LOADK     R3 K299      ; R3 := "KEY2"
815 [230]: SETTABLE  R2 R3 K17    ; R2[R3] := 17
816 [230]: SETTABLE  R0 R1 R2     ; R0[R1] := R2
817 [231]: NEWTABLE  R1 0 2       ; R1 := {}
818 [231]: GETGLOBAL R2 K242      ; R2 := MsgStrID
819 [231]: LOADK     R3 K354      ; R3 := "MSI_HK_FLAG_7"
820 [231]: GETTABLE  R2 R2 R3     ; R2 := R2[R3]
821 [231]: SETTABLE  R1 K241 R2   ; R1["EXE"] := R2
822 [231]: SETTABLE  R1 K244 K73  ; R1["KEY1"] := 55
823 [231]: LOADK     R2 K299      ; R2 := "KEY2"
824 [231]: SETTABLE  R1 R2 K17    ; R1[R2] := 17
825 [231]: SETTABLE  R0 K15 R1    ; R0[16] := R1
826 [232]: NEWTABLE  R1 0 2       ; R1 := {}
827 [232]: GETGLOBAL R2 K242      ; R2 := MsgStrID
828 [232]: LOADK     R3 K355      ; R3 := "MSI_HK_FLAG_8"
829 [232]: GETTABLE  R2 R2 R3     ; R2 := R2[R3]
830 [232]: SETTABLE  R1 K241 R2   ; R1["EXE"] := R2
831 [232]: SETTABLE  R1 K244 K75  ; R1["KEY1"] := 56
832 [232]: LOADK     R2 K299      ; R2 := "KEY2"
833 [232]: SETTABLE  R1 R2 K17    ; R1[R2] := 17
834 [232]: SETTABLE  R0 K17 R1    ; R0[17] := R1
835 [233]: NEWTABLE  R1 0 2       ; R1 := {}
836 [233]: GETGLOBAL R2 K242      ; R2 := MsgStrID
837 [233]: LOADK     R3 K356      ; R3 := "MSI_HK_FLAG_9"
838 [233]: GETTABLE  R2 R2 R3     ; R2 := R2[R3]
839 [233]: SETTABLE  R1 K241 R2   ; R1["EXE"] := R2
840 [233]: SETTABLE  R1 K244 K77  ; R1["KEY1"] := 57
841 [233]: LOADK     R2 K299      ; R2 := "KEY2"
842 [233]: SETTABLE  R1 R2 K17    ; R1[R2] := 17
843 [233]: SETTABLE  R0 K19 R1    ; R0[18] := R1
844 [234]: NEWTABLE  R1 0 2       ; R1 := {}
845 [234]: GETGLOBAL R2 K242      ; R2 := MsgStrID
846 [234]: LOADK     R3 K357      ; R3 := "MSI_HK_FLAG_10"
847 [234]: GETTABLE  R2 R2 R3     ; R2 := R2[R3]
848 [234]: SETTABLE  R1 K241 R2   ; R1["EXE"] := R2
849 [234]: SETTABLE  R1 K244 K59  ; R1["KEY1"] := 48
850 [234]: LOADK     R2 K299      ; R2 := "KEY2"
851 [234]: SETTABLE  R1 R2 K17    ; R1[R2] := 17
852 [234]: SETTABLE  R0 K21 R1    ; R0[19] := R1
853 [235]: SETGLOBAL R0 K337      ; HOTKEY_3 := R0
854 [237]: NEWTABLE  R0 0 0       ; R0 := {}
855 [238]: SETTABLE  R0 K240 K240 ; R0[0] := 0
856 [239]: SETTABLE  R0 K258 K1   ; R0[10] := 1
857 [240]: SETTABLE  R0 K39 K3    ; R0[37] := 2
858 [241]: SETTABLE  R0 K209 K247 ; R0[134] := 3
859 [242]: SETTABLE  R0 K45 K254  ; R0[40] := 7
860 [243]: LOADK     R1 K359      ; R1 := 140
861 [243]: SETTABLE  R0 R1 K7     ; R0[R1] := 8
862 [244]: SETTABLE  R0 K7 K9     ; R0[8] := 9
863 [245]: LOADK     R1 K360      ; R1 := 59
864 [245]: SETTABLE  R0 R1 K258   ; R0[R1] := 10
865 [246]: SETTABLE  R0 K123 K260 ; R0[87] := 11
866 [247]: LOADK     R1 K264      ; R1 := 14
867 [247]: SETTABLE  R0 K121 R1   ; R0[86] := R1
868 [248]: LOADK     R1 K266      ; R1 := 15
869 [248]: SETTABLE  R0 K165 R1   ; R0[112] := R1
870 [249]: SETTABLE  R0 K37 K17   ; R0[36] := 17
871 [250]: LOADK     R1 K361      ; R1 := 137
872 [250]: LOADK     R2 K274      ; R2 := 22
873 [250]: SETTABLE  R0 R1 R2     ; R0[R1] := R2
874 [251]: LOADK     R1 K276      ; R1 := 23
875 [251]: SETTABLE  R0 K125 R1   ; R0[88] := R1
876 [252]: LOADK     R1 K278      ; R1 := 24
877 [252]: SETTABLE  R0 K167 R1   ; R0[113] := R1
878 [253]: SETTABLE  R0 K191 K27  ; R0[125] := 25
879 [254]: LOADK     R1 K362      ; R1 := 157
880 [254]: LOADK     R2 K289      ; R2 := 30
881 [254]: SETTABLE  R0 R1 R2     ; R0[R1] := R2
882 [255]: SETTABLE  R0 K227 K37  ; R0[191] := 36
883 [256]: LOADK     R1 K363      ; R1 := 184
884 [256]: SETTABLE  R0 R1 K39    ; R0[R1] := 37
885 [257]: SETGLOBAL R0 K358      ; BEHAVIOR_TO_WINDOWID := R0
886 [277]: CLOSURE   R0 0         ; R0 := closure(Function #0)
887 [264]: SETGLOBAL R0 K364      ; GetKeyDes := R0
888 [314]: CLOSURE   R0 1         ; R0 := closure(Function #1)
889 [284]: SETGLOBAL R0 K365      ; GetBeHaviorOfWindow := R0
890 [336]: CLOSURE   R0 2         ; R0 := closure(Function #2)
891 [321]: SETGLOBAL R0 K366      ; GetHotKeyInfo := R0
892 [345]: CLOSURE   R0 3         ; R0 := closure(Function #3)
893 [343]: SETGLOBAL R0 K367      ; GetOriginalHotKeyInfo := R0
894 [354]: CLOSURE   R0 4         ; R0 := closure(Function #4)
895 [352]: SETGLOBAL R0 K368      ; GetUserHotKeyInfo := R0
896 [370]: CLOSURE   R0 5         ; R0 := closure(Function #5)
897 [361]: SETGLOBAL R0 K369      ; GetOriginalHotKeyListSize := R0
898 [385]: CLOSURE   R0 6         ; R0 := closure(Function #6)
899 [377]: SETGLOBAL R0 K370      ; GetHotKey := R0
900 [423]: CLOSURE   R0 7         ; R0 := closure(Function #7)
901 [392]: SETGLOBAL R0 K371      ; GetBehaviorOfHotKey := R0
902 [466]: CLOSURE   R0 8         ; R0 := closure(Function #8)
903 [430]: SETGLOBAL R0 K372      ; ChangeUserHotKey := R0
904 [495]: CLOSURE   R0 9         ; R0 := closure(Function #9)
905 [473]: SETGLOBAL R0 K373      ; GetIndexOfTheUserHotKey := R0
906 [523]: CLOSURE   R0 10        ; R0 := closure(Function #10)
907 [502]: SETGLOBAL R0 K374      ; ResetTheHotKey := R0
908 [573]: CLOSURE   R0 11        ; R0 := closure(Function #11)
909 [530]: SETGLOBAL R0 K375      ; SaveUserHotKeys := R0
910 [573]: RETURN    R0 1         ; return 


; Function #0:
;
; Name:            
; Defined at line: 264
; #Upvalues:       0
; #Parameters:     2 (R0, R1)
; Is_vararg:       0
; Max Stack Size:  8
;
; Locals:
; Start PC |  End PC  | Name
; 00000000 | 00000014 | key1
; 00000000 | 00000014 | key2
; 00000002 | 00000014 | keyName1
; 00000004 | 00000014 | keyName2
;
; No upvalues

  1 [265]: GETGLOBAL R2 K0        ; R2 := KEYNAME
  2 [265]: GETTABLE  R2 R2 R0     ; R2 := R2[R0]
  3 [266]: GETGLOBAL R3 K0        ; R3 := KEYNAME
  4 [266]: GETTABLE  R3 R3 R1     ; R3 := R3[R1]
  5 [268]: EQ        0 R2 K1      ; if R2 != nil then PC := 10
  6 [268]: JMP       10
  7 [269]: LOADK     R4 K2        ; R4 := ""
  8 [269]: RETURN    R4 2         ; return R4
  9 [269]: JMP       21           ; PC := 21
 10 [271]: EQ        1 R3 K1      ; if R3 == nil then PC := 20
 11 [271]: JMP       20
 12 [272]: GETGLOBAL R4 K3        ; R4 := string
 13 [272]: GETTABLE  R4 R4 K4     ; R4 := R4["format"]
 14 [272]: LOADK     R5 K5        ; R5 := "%s + %s"
 15 [272]: MOVE      R6 R3        ; R6 := R3
 16 [272]: MOVE      R7 R2        ; R7 := R2
 17 [272]: TAILCALL  R4 4         ; return R4(R5,R6,R7)
 18 [272]: RETURN    R4 0         ; return R4,...
 19 [272]: JMP       21           ; PC := 21
 20 [274]: RETURN    R2 2         ; return R2
 21 [277]: RETURN    R0 1         ; return 


; Function #1:
;
; Name:            
; Defined at line: 284
; #Upvalues:       0
; #Parameters:     1 (R0)
; Is_vararg:       0
; Max Stack Size:  8
;
; Locals:
; Start PC |  End PC  | Name
; 00000000 | 00000025 | winID
; 00000002 | 00000025 | behavior
; 00000005 | 00000022 | userTable
; 00000006 | 00000022 | key1
; 00000006 | 00000022 | key2
;
; No upvalues

  1 [285]: GETGLOBAL R1 K0        ; R1 := BEHAVIOR_TO_WINDOWID
  2 [285]: GETTABLE  R1 R1 R0     ; R1 := R1[R0]
  3 [287]: EQ        1 R1 K1      ; if R1 == nil then PC := 36
  4 [287]: JMP       36
  5 [288]: GETGLOBAL R2 K2        ; R2 := USERKEY_2
  6 [289]: LOADNIL   R3 R4        ; R3 := R4 := nil
  7 [292]: EQ        1 R2 K1      ; if R2 == nil then PC := 17
  8 [292]: JMP       17
  9 [293]: GETGLOBAL R5 K2        ; R5 := USERKEY_2
 10 [293]: GETTABLE  R2 R5 R1     ; R2 := R5[R1]
 11 [295]: EQ        1 R2 K1      ; if R2 == nil then PC := 17
 12 [295]: JMP       17
 13 [295]: EQ        1 R2 K3      ; if R2 == "NULL" then PC := 17
 14 [295]: JMP       17
 15 [296]: GETTABLE  R3 R2 K4     ; R3 := R2["KEY1"]
 16 [297]: GETTABLE  R4 R2 K5     ; R4 := R2["KEY2"]
 17 [301]: EQ        0 R3 K1      ; if R3 != nil then PC := 25
 18 [301]: JMP       25
 19 [302]: GETGLOBAL R5 K6        ; R5 := HOTKEY_2
 20 [302]: GETTABLE  R5 R5 R1     ; R5 := R5[R1]
 21 [302]: GETTABLE  R3 R5 K4     ; R3 := R5["KEY1"]
 22 [303]: GETGLOBAL R5 K6        ; R5 := HOTKEY_2
 23 [303]: GETTABLE  R5 R5 R1     ; R5 := R5[R1]
 24 [303]: GETTABLE  R4 R5 K5     ; R4 := R5["KEY2"]
 25 [306]: EQ        1 R3 K1      ; if R3 == nil then PC := 33
 26 [306]: JMP       33
 27 [307]: GETGLOBAL R5 K7        ; R5 := GetKeyDes
 28 [307]: MOVE      R6 R3        ; R6 := R3
 29 [307]: MOVE      R7 R4        ; R7 := R4
 30 [307]: TAILCALL  R5 3         ; return R5(R6,R7)
 31 [307]: RETURN    R5 0         ; return R5,...
 32 [307]: JMP       38           ; PC := 38
 33 [309]: LOADK     R5 K8        ; R5 := ""
 34 [309]: RETURN    R5 2         ; return R5
 35 [310]: JMP       38           ; PC := 38
 36 [312]: LOADK     R2 K8        ; R2 := ""
 37 [312]: RETURN    R2 2         ; return R2
 38 [314]: RETURN    R0 1         ; return 


; Function #2:
;
; Name:            
; Defined at line: 321
; #Upvalues:       0
; #Parameters:     2 (R0, R1)
; Is_vararg:       0
; Max Stack Size:  8
;
; Locals:
; Start PC |  End PC  | Name
; 00000000 | 00000038 | tableName
; 00000000 | 00000038 | idx
;
; No upvalues

  1 [322]: GETGLOBAL R2 K1        ; R2 := _G
  2 [322]: GETTABLE  R2 R2 R0     ; R2 := R2[R0]
  3 [322]: SETGLOBAL R2 K0        ; element := R2
  4 [324]: GETGLOBAL R2 K0        ; R2 := element
  5 [324]: EQ        1 R2 K2      ; if R2 == nil then PC := 48
  6 [324]: JMP       48
  7 [325]: GETGLOBAL R2 K0        ; R2 := element
  8 [325]: GETTABLE  R2 R2 R1     ; R2 := R2[R1]
  9 [325]: SETGLOBAL R2 K3        ; v := R2
 10 [327]: GETGLOBAL R2 K3        ; R2 := v
 11 [327]: EQ        1 R2 K2      ; if R2 == nil then PC := 16
 12 [327]: JMP       16
 13 [327]: GETGLOBAL R2 K3        ; R2 := v
 14 [327]: EQ        0 R2 K4      ; if R2 != "NULL" then PC := 26
 15 [327]: JMP       26
 16 [328]: LOADK     R2 K5        ; R2 := 0
 17 [328]: LOADK     R3 K5        ; R3 := 0
 18 [328]: GETGLOBAL R4 K6        ; R4 := toStr
 19 [328]: LOADK     R5 K7        ; R5 := ""
 20 [328]: CALL      R4 2 2       ; R4 := R4(R5)
 21 [328]: GETGLOBAL R5 K6        ; R5 := toStr
 22 [328]: LOADK     R6 K7        ; R6 := ""
 23 [328]: CALL      R5 2 0       ; R5,... := R5(R6)
 24 [328]: RETURN    R2 0         ; return R2,...
 25 [328]: JMP       57           ; PC := 57
 26 [330]: GETGLOBAL R2 K8        ; R2 := toInt
 27 [330]: GETGLOBAL R3 K3        ; R3 := v
 28 [330]: GETTABLE  R3 R3 K9     ; R3 := R3["KEY1"]
 29 [330]: CALL      R2 2 2       ; R2 := R2(R3)
 30 [330]: GETGLOBAL R3 K8        ; R3 := toInt
 31 [330]: GETGLOBAL R4 K3        ; R4 := v
 32 [330]: GETTABLE  R4 R4 K10    ; R4 := R4["KEY2"]
 33 [330]: CALL      R3 2 2       ; R3 := R3(R4)
 34 [330]: GETGLOBAL R4 K6        ; R4 := toStr
 35 [330]: GETGLOBAL R5 K11       ; R5 := GetKeyDes
 36 [330]: GETGLOBAL R6 K3        ; R6 := v
 37 [330]: GETTABLE  R6 R6 K9     ; R6 := R6["KEY1"]
 38 [330]: GETGLOBAL R7 K3        ; R7 := v
 39 [330]: GETTABLE  R7 R7 K10    ; R7 := R7["KEY2"]
 40 [330]: CALL      R5 3 0       ; R5,... := R5(R6,R7)
 41 [330]: CALL      R4 0 2       ; R4 := R4(R5,...)
 42 [330]: GETGLOBAL R5 K6        ; R5 := toStr
 43 [330]: GETGLOBAL R6 K3        ; R6 := v
 44 [330]: GETTABLE  R6 R6 K12    ; R6 := R6["EXE"]
 45 [330]: CALL      R5 2 0       ; R5,... := R5(R6)
 46 [330]: RETURN    R2 0         ; return R2,...
 47 [331]: JMP       57           ; PC := 57
 48 [333]: LOADK     R2 K5        ; R2 := 0
 49 [333]: LOADK     R3 K5        ; R3 := 0
 50 [333]: GETGLOBAL R4 K6        ; R4 := toStr
 51 [333]: LOADK     R5 K7        ; R5 := ""
 52 [333]: CALL      R4 2 2       ; R4 := R4(R5)
 53 [333]: GETGLOBAL R5 K6        ; R5 := toStr
 54 [333]: LOADK     R6 K7        ; R6 := ""
 55 [333]: CALL      R5 2 0       ; R5,... := R5(R6)
 56 [333]: RETURN    R2 0         ; return R2,...
 57 [336]: RETURN    R0 1         ; return 


; Function #3:
;
; Name:            
; Defined at line: 343
; #Upvalues:       0
; #Parameters:     2 (R0, R1)
; Is_vararg:       0
; Max Stack Size:  6
;
; Locals:
; Start PC |  End PC  | Name
; 00000000 | 00000009 | tabNum
; 00000000 | 00000009 | idx
;
; No upvalues

  1 [344]: GETGLOBAL R2 K0        ; R2 := GetHotKeyInfo
  2 [344]: GETGLOBAL R3 K1        ; R3 := string
  3 [344]: GETTABLE  R3 R3 K2     ; R3 := R3["format"]
  4 [344]: LOADK     R4 K3        ; R4 := "HOTKEY_%d"
  5 [344]: MOVE      R5 R0        ; R5 := R0
  6 [344]: CALL      R3 3 2       ; R3 := R3(R4,R5)
  7 [344]: MOVE      R4 R1        ; R4 := R1
  8 [344]: TAILCALL  R2 3         ; return R2(R3,R4)
  9 [344]: RETURN    R2 0         ; return R2,...
 10 [345]: RETURN    R0 1         ; return 


; Function #4:
;
; Name:            
; Defined at line: 352
; #Upvalues:       0
; #Parameters:     2 (R0, R1)
; Is_vararg:       0
; Max Stack Size:  6
;
; Locals:
; Start PC |  End PC  | Name
; 00000000 | 00000009 | tabNum
; 00000000 | 00000009 | idx
;
; No upvalues

  1 [353]: GETGLOBAL R2 K0        ; R2 := GetHotKeyInfo
  2 [353]: GETGLOBAL R3 K1        ; R3 := string
  3 [353]: GETTABLE  R3 R3 K2     ; R3 := R3["format"]
  4 [353]: LOADK     R4 K3        ; R4 := "USERKEY_%d"
  5 [353]: MOVE      R5 R0        ; R5 := R0
  6 [353]: CALL      R3 3 2       ; R3 := R3(R4,R5)
  7 [353]: MOVE      R4 R1        ; R4 := R1
  8 [353]: TAILCALL  R2 3         ; return R2(R3,R4)
  9 [353]: RETURN    R2 0         ; return R2,...
 10 [354]: RETURN    R0 1         ; return 


; Function #5:
;
; Name:            
; Defined at line: 361
; #Upvalues:       0
; #Parameters:     1 (R0)
; Is_vararg:       0
; Max Stack Size:  7
;
; Locals:
; Start PC |  End PC  | Name
; 00000000 | 00000017 | tabNum
; 00000001 | 00000017 | tableSize
;
; No upvalues

  1 [362]: LOADK     R1 K0        ; R1 := 0
  2 [363]: GETGLOBAL R2 K2        ; R2 := _G
  3 [363]: GETGLOBAL R3 K3        ; R3 := string
  4 [363]: GETTABLE  R3 R3 K4     ; R3 := R3["format"]
  5 [363]: LOADK     R4 K5        ; R4 := "HOTKEY_%d"
  6 [363]: MOVE      R5 R0        ; R5 := R0
  7 [363]: CALL      R3 3 2       ; R3 := R3(R4,R5)
  8 [363]: GETTABLE  R2 R2 R3     ; R2 := R2[R3]
  9 [363]: SETGLOBAL R2 K1        ; table := R2
 10 [365]: GETGLOBAL R2 K1        ; R2 := table
 11 [365]: EQ        1 R2 K6      ; if R2 == nil then PC := 23
 12 [365]: JMP       23
 13 [366]: GETGLOBAL R2 K7        ; R2 := getTableSize
 14 [366]: GETGLOBAL R3 K2        ; R3 := _G
 15 [366]: GETGLOBAL R4 K3        ; R4 := string
 16 [366]: GETTABLE  R4 R4 K4     ; R4 := R4["format"]
 17 [366]: LOADK     R5 K5        ; R5 := "HOTKEY_%d"
 18 [366]: MOVE      R6 R0        ; R6 := R0
 19 [366]: CALL      R4 3 2       ; R4 := R4(R5,R6)
 20 [366]: GETTABLE  R3 R3 R4     ; R3 := R3[R4]
 21 [366]: CALL      R2 2 2       ; R2 := R2(R3)
 22 [366]: MOVE      R1 R2        ; R1 := R2
 23 [369]: RETURN    R1 2         ; return R1
 24 [370]: RETURN    R0 1         ; return 


; Function #6:
;
; Name:            
; Defined at line: 377
; #Upvalues:       0
; #Parameters:     2 (R0, R1)
; Is_vararg:       0
; Max Stack Size:  6
;
; Locals:
; Start PC |  End PC  | Name
; 00000000 | 00000015 | tabNum
; 00000000 | 00000015 | idx
;
; No upvalues

  1 [378]: GETGLOBAL R2 K4        ; R2 := GetUserHotKeyInfo
  2 [378]: MOVE      R3 R0        ; R3 := R0
  3 [378]: MOVE      R4 R1        ; R4 := R1
  4 [378]: CALL      R2 3 5       ; R2,R3,R4,R5 := R2(R3,R4)
  5 [378]: SETGLOBAL R5 K3        ; exe := R5
  6 [378]: SETGLOBAL R4 K2        ; des := R4
  7 [378]: SETGLOBAL R3 K1        ; key2 := R3
  8 [378]: SETGLOBAL R2 K0        ; key1 := R2
  9 [380]: GETGLOBAL R2 K3        ; R2 := exe
 10 [380]: EQ        0 R2 K5      ; if R2 != "" then PC := 17
 11 [380]: JMP       17
 12 [381]: GETGLOBAL R2 K6        ; R2 := GetOriginalHotKeyInfo
 13 [381]: MOVE      R3 R0        ; R3 := R0
 14 [381]: MOVE      R4 R1        ; R4 := R1
 15 [381]: TAILCALL  R2 3         ; return R2(R3,R4)
 16 [381]: RETURN    R2 0         ; return R2,...
 17 [384]: GETGLOBAL R2 K0        ; R2 := key1
 18 [384]: GETGLOBAL R3 K1        ; R3 := key2
 19 [384]: GETGLOBAL R4 K2        ; R4 := des
 20 [384]: GETGLOBAL R5 K3        ; R5 := exe
 21 [384]: RETURN    R2 5         ; return R2,R3,R4,R5
 22 [385]: RETURN    R0 1         ; return 


; Function #7:
;
; Name:            
; Defined at line: 392
; #Upvalues:       0
; #Parameters:     2 (R0, R1)
; Is_vararg:       0
; Max Stack Size:  6
;
; Locals:
; Start PC |  End PC  | Name
; 00000000 | 0000004c | inKey1
; 00000000 | 0000004c | inKey2
;
; No upvalues

  1 [393]: LOADK     R2 K1        ; R2 := 0
  2 [393]: SETGLOBAL R2 K0        ; size := R2
  3 [394]: LOADK     R2 K3        ; R2 := 1
  4 [394]: SETGLOBAL R2 K2        ; tab := R2
  5 [395]: GETGLOBAL R2 K5        ; R2 := GetOriginalHotKeyListSize
  6 [395]: GETGLOBAL R3 K2        ; R3 := tab
  7 [395]: CALL      R2 2 2       ; R2 := R2(R3)
  8 [395]: SETGLOBAL R2 K4        ; tableLen := R2
  9 [397]: JMP       72           ; PC := 72
 10 [398]: LOADK     R2 K1        ; R2 := 0
 11 [398]: SETGLOBAL R2 K6        ; idx := R2
 12 [399]: GETGLOBAL R2 K11       ; R2 := GetHotKey
 13 [399]: GETGLOBAL R3 K2        ; R3 := tab
 14 [399]: GETGLOBAL R4 K6        ; R4 := idx
 15 [399]: CALL      R2 3 5       ; R2,R3,R4,R5 := R2(R3,R4)
 16 [399]: SETGLOBAL R5 K10       ; exe := R5
 17 [399]: SETGLOBAL R4 K9        ; des := R4
 18 [399]: SETGLOBAL R3 K8        ; key2 := R3
 19 [399]: SETGLOBAL R2 K7        ; key1 := R2
 20 [401]: JMP       58           ; PC := 58
 21 [402]: GETGLOBAL R2 K10       ; R2 := exe
 22 [402]: GETGLOBAL R3 K13       ; R3 := MsgStrID
 23 [402]: GETTABLE  R3 R3 K14    ; R3 := R3["MSI_HK_CHATMODE_ONOFF"]
 24 [402]: EQ        0 R2 R3      ; if R2 != R3 then PC := 35
 25 [402]: JMP       35
 26 [403]: GETGLOBAL R2 K7        ; R2 := key1
 27 [403]: EQ        0 R2 R0      ; if R2 != R0 then PC := 35
 28 [403]: JMP       35
 29 [404]: GETGLOBAL R2 K6        ; R2 := idx
 30 [404]: GETGLOBAL R3 K2        ; R3 := tab
 31 [404]: SUB       R3 R3 K3     ; R3 := R3 - 1
 32 [404]: MUL       R3 R3 K15    ; R3 := R3 * 100
 33 [404]: ADD       R2 R2 R3     ; R2 := R2 + R3
 34 [404]: RETURN    R2 2         ; return R2
 35 [408]: GETGLOBAL R2 K7        ; R2 := key1
 36 [408]: EQ        0 R2 R0      ; if R2 != R0 then PC := 47
 37 [408]: JMP       47
 38 [408]: GETGLOBAL R2 K8        ; R2 := key2
 39 [408]: EQ        0 R2 R1      ; if R2 != R1 then PC := 47
 40 [408]: JMP       47
 41 [409]: GETGLOBAL R2 K6        ; R2 := idx
 42 [409]: GETGLOBAL R3 K2        ; R3 := tab
 43 [409]: SUB       R3 R3 K3     ; R3 := R3 - 1
 44 [409]: MUL       R3 R3 K15    ; R3 := R3 * 100
 45 [409]: ADD       R2 R2 R3     ; R2 := R2 + R3
 46 [409]: RETURN    R2 2         ; return R2
 47 [412]: GETGLOBAL R2 K6        ; R2 := idx
 48 [412]: ADD       R2 R2 K3     ; R2 := R2 + 1
 49 [412]: SETGLOBAL R2 K6        ; idx := R2
 50 [413]: GETGLOBAL R2 K11       ; R2 := GetHotKey
 51 [413]: GETGLOBAL R3 K2        ; R3 := tab
 52 [413]: GETGLOBAL R4 K6        ; R4 := idx
 53 [413]: CALL      R2 3 5       ; R2,R3,R4,R5 := R2(R3,R4)
 54 [413]: SETGLOBAL R5 K10       ; exe := R5
 55 [413]: SETGLOBAL R4 K9        ; des := R4
 56 [413]: SETGLOBAL R3 K8        ; key2 := R3
 57 [413]: SETGLOBAL R2 K7        ; key1 := R2
 58 [401]: GETGLOBAL R2 K10       ; R2 := exe
 59 [401]: EQ        0 R2 K12     ; if R2 != "" then PC := 21
 60 [401]: JMP       21
 61 [416]: GETGLOBAL R2 K0        ; R2 := size
 62 [416]: GETGLOBAL R3 K4        ; R3 := tableLen
 63 [416]: ADD       R2 R2 R3     ; R2 := R2 + R3
 64 [416]: SETGLOBAL R2 K0        ; size := R2
 65 [418]: GETGLOBAL R2 K2        ; R2 := tab
 66 [418]: ADD       R2 R2 K3     ; R2 := R2 + 1
 67 [418]: SETGLOBAL R2 K2        ; tab := R2
 68 [419]: GETGLOBAL R2 K5        ; R2 := GetOriginalHotKeyListSize
 69 [419]: GETGLOBAL R3 K2        ; R3 := tab
 70 [419]: CALL      R2 2 2       ; R2 := R2(R3)
 71 [419]: SETGLOBAL R2 K4        ; tableLen := R2
 72 [397]: GETGLOBAL R2 K4        ; R2 := tableLen
 73 [397]: EQ        0 R2 K1      ; if R2 != 0 then PC := 10
 74 [397]: JMP       10
 75 [422]: LOADK     R2 K16       ; R2 := -1
 76 [422]: RETURN    R2 2         ; return R2
 77 [423]: RETURN    R0 1         ; return 


; Function #8:
;
; Name:            
; Defined at line: 430
; #Upvalues:       0
; #Parameters:     5 (R0, R1, R2, R3, R4)
; Is_vararg:       0
; Max Stack Size:  9
;
; Locals:
; Start PC |  End PC  | Name
; 00000000 | 00000043 | tabNum
; 00000000 | 00000043 | idx
; 00000000 | 00000043 | exe
; 00000000 | 00000043 | key1
; 00000000 | 00000043 | key2
;
; No upvalues

  1 [431]: GETGLOBAL R5 K1        ; R5 := string
  2 [431]: GETTABLE  R5 R5 K2     ; R5 := R5["format"]
  3 [431]: LOADK     R6 K3        ; R6 := "USERKEY_%d"
  4 [431]: MOVE      R7 R0        ; R7 := R0
  5 [431]: CALL      R5 3 2       ; R5 := R5(R6,R7)
  6 [431]: SETGLOBAL R5 K0        ; TableName := R5
  7 [432]: GETGLOBAL R5 K5        ; R5 := _G
  8 [432]: GETGLOBAL R6 K0        ; R6 := TableName
  9 [432]: GETTABLE  R5 R5 R6     ; R5 := R5[R6]
 10 [432]: SETGLOBAL R5 K4        ; UserKeyTable := R5
 11 [434]: GETGLOBAL R5 K9        ; R5 := GetOriginalHotKeyInfo
 12 [434]: MOVE      R6 R0        ; R6 := R0
 13 [434]: MOVE      R7 R1        ; R7 := R1
 14 [434]: CALL      R5 3 5       ; R5,R6,R7,R8 := R5(R6,R7)
 15 [434]: MOVE      R2 R8        ; R2 := R8
 16 [434]: SETGLOBAL R7 K8        ; dis := R7
 17 [434]: SETGLOBAL R6 K7        ; originalKey2 := R6
 18 [434]: SETGLOBAL R5 K6        ; originalKey1 := R5
 19 [437]: GETGLOBAL R5 K1        ; R5 := string
 20 [437]: GETTABLE  R5 R5 K10    ; R5 := R5["len"]
 21 [437]: MOVE      R6 R2        ; R6 := R2
 22 [437]: CALL      R5 2 2       ; R5 := R5(R6)
 23 [437]: EQ        1 R5 K11     ; if R5 == 0 then PC := 37
 24 [437]: JMP       37
 25 [438]: GETGLOBAL R5 K6        ; R5 := originalKey1
 26 [438]: EQ        0 R3 R5      ; if R3 != R5 then PC := 37
 27 [438]: JMP       37
 28 [438]: GETGLOBAL R5 K7        ; R5 := originalKey2
 29 [438]: EQ        0 R4 R5      ; if R4 != R5 then PC := 37
 30 [438]: JMP       37
 31 [439]: GETGLOBAL R5 K4        ; R5 := UserKeyTable
 32 [439]: EQ        1 R5 K12     ; if R5 == nil then PC := 37
 33 [439]: JMP       37
 34 [440]: GETGLOBAL R5 K4        ; R5 := UserKeyTable
 35 [440]: SETTABLE  R5 R1 K12    ; R5[R1] := nil
 36 [441]: RETURN    R0 1         ; return 
 37 [446]: GETGLOBAL R5 K4        ; R5 := UserKeyTable
 38 [446]: EQ        0 R5 K12     ; if R5 != nil then PC := 42
 39 [446]: JMP       42
 40 [447]: NEWTABLE  R5 0 0       ; R5 := {}
 41 [447]: SETGLOBAL R5 K4        ; UserKeyTable := R5
 42 [450]: GETGLOBAL R5 K4        ; R5 := UserKeyTable
 43 [450]: GETTABLE  R5 R5 R1     ; R5 := R5[R1]
 44 [450]: SETGLOBAL R5 K13       ; UserKey := R5
 45 [452]: GETGLOBAL R5 K13       ; R5 := UserKey
 46 [452]: EQ        0 R5 K14     ; if R5 != "NULL" then PC := 50
 47 [452]: JMP       50
 48 [453]: LOADNIL   R5 R5        ; R5 := nil
 49 [453]: SETGLOBAL R5 K13       ; UserKey := R5
 50 [456]: GETGLOBAL R5 K13       ; R5 := UserKey
 51 [456]: EQ        0 R5 K12     ; if R5 != nil then PC := 55
 52 [456]: JMP       55
 53 [457]: NEWTABLE  R5 0 0       ; R5 := {}
 54 [457]: SETGLOBAL R5 K13       ; UserKey := R5
 55 [460]: GETGLOBAL R5 K13       ; R5 := UserKey
 56 [460]: SETTABLE  R5 K15 R2    ; R5["EXE"] := R2
 57 [461]: GETGLOBAL R5 K13       ; R5 := UserKey
 58 [461]: SETTABLE  R5 K16 R3    ; R5["KEY1"] := R3
 59 [462]: GETGLOBAL R5 K13       ; R5 := UserKey
 60 [462]: SETTABLE  R5 K17 R4    ; R5["KEY2"] := R4
 61 [464]: GETGLOBAL R5 K4        ; R5 := UserKeyTable
 62 [464]: GETGLOBAL R6 K13       ; R6 := UserKey
 63 [464]: SETTABLE  R5 R1 R6     ; R5[R1] := R6
 64 [465]: GETGLOBAL R5 K5        ; R5 := _G
 65 [465]: GETGLOBAL R6 K0        ; R6 := TableName
 66 [465]: GETGLOBAL R7 K4        ; R7 := UserKeyTable
 67 [465]: SETTABLE  R5 R6 R7     ; R5[R6] := R7
 68 [466]: RETURN    R0 1         ; return 


; Function #9:
;
; Name:            
; Defined at line: 473
; #Upvalues:       0
; #Parameters:     2 (R0, R1)
; Is_vararg:       0
; Max Stack Size:  6
;
; Locals:
; Start PC |  End PC  | Name
; 00000000 | 00000035 | inKey1
; 00000000 | 00000035 | inKey2
;
; No upvalues

  1 [474]: LOADK     R2 K1        ; R2 := 1
  2 [474]: SETGLOBAL R2 K0        ; tab := R2
  3 [475]: GETGLOBAL R2 K3        ; R2 := GetOriginalHotKeyListSize
  4 [475]: GETGLOBAL R3 K0        ; R3 := tab
  5 [475]: CALL      R2 2 2       ; R2 := R2(R3)
  6 [475]: SETGLOBAL R2 K2        ; tableLen := R2
  7 [477]: JMP       49           ; PC := 49
  8 [478]: LOADK     R2 K4        ; R2 := 0
  9 [478]: SETGLOBAL R2 K5        ; idx := R2
 10 [479]: GETGLOBAL R2 K10       ; R2 := GetUserHotKeyInfo
 11 [479]: GETGLOBAL R3 K0        ; R3 := tab
 12 [479]: GETGLOBAL R4 K5        ; R4 := idx
 13 [479]: CALL      R2 3 5       ; R2,R3,R4,R5 := R2(R3,R4)
 14 [479]: SETGLOBAL R5 K9        ; exe := R5
 15 [479]: SETGLOBAL R4 K8        ; des := R4
 16 [479]: SETGLOBAL R3 K7        ; key2 := R3
 17 [479]: SETGLOBAL R2 K6        ; key1 := R2
 18 [481]: JMP       38           ; PC := 38
 19 [482]: GETGLOBAL R2 K6        ; R2 := key1
 20 [482]: EQ        0 R2 R0      ; if R2 != R0 then PC := 27
 21 [482]: JMP       27
 22 [482]: GETGLOBAL R2 K7        ; R2 := key2
 23 [482]: EQ        0 R2 R1      ; if R2 != R1 then PC := 27
 24 [482]: JMP       27
 25 [483]: GETGLOBAL R2 K5        ; R2 := idx
 26 [483]: RETURN    R2 2         ; return R2
 27 [486]: GETGLOBAL R2 K5        ; R2 := idx
 28 [486]: ADD       R2 R2 K1     ; R2 := R2 + 1
 29 [486]: SETGLOBAL R2 K5        ; idx := R2
 30 [487]: GETGLOBAL R2 K10       ; R2 := GetUserHotKeyInfo
 31 [487]: GETGLOBAL R3 K0        ; R3 := tab
 32 [487]: GETGLOBAL R4 K5        ; R4 := idx
 33 [487]: CALL      R2 3 5       ; R2,R3,R4,R5 := R2(R3,R4)
 34 [487]: SETGLOBAL R5 K9        ; exe := R5
 35 [487]: SETGLOBAL R4 K8        ; des := R4
 36 [487]: SETGLOBAL R3 K7        ; key2 := R3
 37 [487]: SETGLOBAL R2 K6        ; key1 := R2
 38 [481]: GETGLOBAL R2 K5        ; R2 := idx
 39 [481]: GETGLOBAL R3 K2        ; R3 := tableLen
 40 [481]: LT        1 R2 R3      ; if R2 < R3 then PC := 19
 41 [481]: JMP       19
 42 [490]: GETGLOBAL R2 K0        ; R2 := tab
 43 [490]: ADD       R2 R2 K1     ; R2 := R2 + 1
 44 [490]: SETGLOBAL R2 K0        ; tab := R2
 45 [491]: GETGLOBAL R2 K3        ; R2 := GetOriginalHotKeyListSize
 46 [491]: GETGLOBAL R3 K0        ; R3 := tab
 47 [491]: CALL      R2 2 2       ; R2 := R2(R3)
 48 [491]: SETGLOBAL R2 K2        ; tableLen := R2
 49 [477]: GETGLOBAL R2 K2        ; R2 := tableLen
 50 [477]: EQ        0 R2 K4      ; if R2 != 0 then PC := 8
 51 [477]: JMP       8
 52 [494]: LOADK     R2 K11       ; R2 := -1
 53 [494]: RETURN    R2 2         ; return R2
 54 [495]: RETURN    R0 1         ; return 


; Function #10:
;
; Name:            
; Defined at line: 502
; #Upvalues:       0
; #Parameters:     4 (R0, R1, R2, R3)
; Is_vararg:       0
; Max Stack Size:  8
;
; Locals:
; Start PC |  End PC  | Name
; 00000000 | 0000002e | tabNum
; 00000000 | 0000002e | idx
; 00000000 | 0000002e | inKey1
; 00000000 | 0000002e | inKey2
;
; No upvalues

  1 [503]: GETGLOBAL R4 K1        ; R4 := GetOriginalHotKeyListSize
  2 [503]: MOVE      R5 R0        ; R5 := R0
  3 [503]: CALL      R4 2 2       ; R4 := R4(R5)
  4 [503]: SETGLOBAL R4 K0        ; tableLen := R4
  5 [504]: GETGLOBAL R4 K0        ; R4 := tableLen
  6 [504]: SUB       R1 R1 R4     ; R1 := R1 - R4
  7 [505]: ADD       R0 R0 K2     ; R0 := R0 + 1
  8 [507]: GETGLOBAL R4 K4        ; R4 := string
  9 [507]: GETTABLE  R4 R4 K5     ; R4 := R4["format"]
 10 [507]: LOADK     R5 K6        ; R5 := "USERKEY_%d"
 11 [507]: MOVE      R6 R0        ; R6 := R0
 12 [507]: CALL      R4 3 2       ; R4 := R4(R5,R6)
 13 [507]: SETGLOBAL R4 K3        ; TableName := R4
 14 [508]: GETGLOBAL R4 K8        ; R4 := _G
 15 [508]: GETGLOBAL R5 K3        ; R5 := TableName
 16 [508]: GETTABLE  R4 R4 R5     ; R4 := R4[R5]
 17 [508]: SETGLOBAL R4 K7        ; UserKeyTable := R4
 18 [510]: GETGLOBAL R4 K7        ; R4 := UserKeyTable
 19 [510]: EQ        0 R4 K9      ; if R4 != nil then PC := 22
 20 [510]: JMP       22
 21 [511]: RETURN    R0 1         ; return 
 22 [514]: GETGLOBAL R4 K14       ; R4 := GetUserHotKeyInfo
 23 [514]: MOVE      R5 R0        ; R5 := R0
 24 [514]: MOVE      R6 R1        ; R6 := R1
 25 [514]: CALL      R4 3 5       ; R4,R5,R6,R7 := R4(R5,R6)
 26 [514]: SETGLOBAL R7 K13       ; exe := R7
 27 [514]: SETGLOBAL R6 K12       ; des := R6
 28 [514]: SETGLOBAL R5 K11       ; key2 := R5
 29 [514]: SETGLOBAL R4 K10       ; key1 := R4
 30 [516]: GETGLOBAL R4 K10       ; R4 := key1
 31 [516]: EQ        0 R4 K15     ; if R4 != 0 then PC := 47
 32 [516]: JMP       47
 33 [516]: GETGLOBAL R4 K11       ; R4 := key2
 34 [516]: EQ        0 R4 K15     ; if R4 != 0 then PC := 47
 35 [516]: JMP       47
 36 [517]: GETGLOBAL R4 K17       ; R4 := GetIndexOfTheUserHotKey
 37 [517]: MOVE      R5 R2        ; R5 := R2
 38 [517]: MOVE      R6 R3        ; R6 := R3
 39 [517]: CALL      R4 3 2       ; R4 := R4(R5,R6)
 40 [517]: SETGLOBAL R4 K16       ; idx2 := R4
 41 [519]: GETGLOBAL R4 K16       ; R4 := idx2
 42 [519]: EQ        1 R4 K18     ; if R4 == -1 then PC := 47
 43 [519]: JMP       47
 44 [520]: GETGLOBAL R4 K7        ; R4 := UserKeyTable
 45 [520]: GETGLOBAL R5 K16       ; R5 := idx2
 46 [520]: SETTABLE  R4 R5 K9     ; R4[R5] := nil
 47 [523]: RETURN    R0 1         ; return 


; Function #11:
;
; Name:            
; Defined at line: 530
; #Upvalues:       0
; #Parameters:     1 (R0)
; Is_vararg:       0
; Max Stack Size:  7
;
; Locals:
; Start PC |  End PC  | Name
; 00000000 | 00000071 | saveFileName
;
; No upvalues

  1 [531]: GETGLOBAL R1 K1        ; R1 := io
  2 [531]: GETTABLE  R1 R1 K2     ; R1 := R1["open"]
  3 [531]: MOVE      R2 R0        ; R2 := R0
  4 [531]: LOADK     R3 K3        ; R3 := "w"
  5 [531]: CALL      R1 3 2       ; R1 := R1(R2,R3)
  6 [531]: SETGLOBAL R1 K0        ; saveFile := R1
  7 [533]: GETGLOBAL R1 K0        ; R1 := saveFile
  8 [533]: EQ        1 R1 K4      ; if R1 == nil then PC := 110
  9 [533]: JMP       110
 10 [534]: LOADK     R1 K6        ; R1 := 1
 11 [534]: SETGLOBAL R1 K5        ; tabNum := R1
 12 [536]: JMP       107          ; PC := 107
 13 [537]: GETGLOBAL R1 K9        ; R1 := _G
 14 [537]: GETGLOBAL R2 K10       ; R2 := string
 15 [537]: GETTABLE  R2 R2 K11    ; R2 := R2["format"]
 16 [537]: LOADK     R3 K12       ; R3 := "USERKEY_%d"
 17 [537]: GETGLOBAL R4 K5        ; R4 := tabNum
 18 [537]: CALL      R2 3 2       ; R2 := R2(R3,R4)
 19 [537]: GETTABLE  R1 R1 R2     ; R1 := R1[R2]
 20 [537]: SETGLOBAL R1 K8        ; userTable := R1
 21 [539]: GETGLOBAL R1 K8        ; R1 := userTable
 22 [539]: EQ        1 R1 K4      ; if R1 == nil then PC := 104
 23 [539]: JMP       104
 24 [540]: GETGLOBAL R1 K0        ; R1 := saveFile
 25 [540]: SELF      R1 R1 K13    ; R2 := R1; R1 := R1["write"]
 26 [540]: GETGLOBAL R3 K10       ; R3 := string
 27 [540]: GETTABLE  R3 R3 K11    ; R3 := R3["format"]
 28 [540]: LOADK     R4 K14       ; R4 := "USERKEY_%d = {\n"
 29 [540]: GETGLOBAL R5 K5        ; R5 := tabNum
 30 [540]: CALL      R3 3 0       ; R3,... := R3(R4,R5)
 31 [540]: CALL      R1 0 1       ; R1(R2,...)
 32 [542]: LOADK     R1 K16       ; R1 := 0
 33 [542]: SETGLOBAL R1 K15       ; idx := R1
 34 [543]: GETGLOBAL R1 K21       ; R1 := GetUserHotKeyInfo
 35 [543]: GETGLOBAL R2 K5        ; R2 := tabNum
 36 [543]: GETGLOBAL R3 K15       ; R3 := idx
 37 [543]: CALL      R1 3 5       ; R1,R2,R3,R4 := R1(R2,R3)
 38 [543]: SETGLOBAL R4 K20       ; behaviorDes := R4
 39 [543]: SETGLOBAL R3 K19       ; keyDes := R3
 40 [543]: SETGLOBAL R2 K18       ; key2 := R2
 41 [543]: SETGLOBAL R1 K17       ; key1 := R1
 42 [545]: GETGLOBAL R1 K23       ; R1 := GetOriginalHotKeyListSize
 43 [545]: GETGLOBAL R2 K5        ; R2 := tabNum
 44 [545]: CALL      R1 2 2       ; R1 := R1(R2)
 45 [545]: SETGLOBAL R1 K22       ; tableLen := R1
 46 [547]: JMP       96           ; PC := 96
 47 [548]: GETGLOBAL R1 K20       ; R1 := behaviorDes
 48 [548]: EQ        1 R1 K24     ; if R1 == "" then PC := 85
 49 [548]: JMP       85
 50 [549]: GETGLOBAL R1 K0        ; R1 := saveFile
 51 [549]: SELF      R1 R1 K13    ; R2 := R1; R1 := R1["write"]
 52 [549]: GETGLOBAL R3 K10       ; R3 := string
 53 [549]: GETTABLE  R3 R3 K11    ; R3 := R3["format"]
 54 [549]: LOADK     R4 K25       ; R4 := "\t[%d] = { EXE = \"%s\""
 55 [549]: GETGLOBAL R5 K15       ; R5 := idx
 56 [549]: GETGLOBAL R6 K20       ; R6 := behaviorDes
 57 [549]: CALL      R3 4 0       ; R3,... := R3(R4,R5,R6)
 58 [549]: CALL      R1 0 1       ; R1(R2,...)
 59 [551]: GETGLOBAL R1 K17       ; R1 := key1
 60 [551]: EQ        1 R1 K16     ; if R1 == 0 then PC := 70
 61 [551]: JMP       70
 62 [552]: GETGLOBAL R1 K0        ; R1 := saveFile
 63 [552]: SELF      R1 R1 K13    ; R2 := R1; R1 := R1["write"]
 64 [552]: GETGLOBAL R3 K10       ; R3 := string
 65 [552]: GETTABLE  R3 R3 K11    ; R3 := R3["format"]
 66 [552]: LOADK     R4 K26       ; R4 := ", KEY1 = %d"
 67 [552]: GETGLOBAL R5 K17       ; R5 := key1
 68 [552]: CALL      R3 3 0       ; R3,... := R3(R4,R5)
 69 [552]: CALL      R1 0 1       ; R1(R2,...)
 70 [555]: GETGLOBAL R1 K18       ; R1 := key2
 71 [555]: EQ        1 R1 K16     ; if R1 == 0 then PC := 81
 72 [555]: JMP       81
 73 [556]: GETGLOBAL R1 K0        ; R1 := saveFile
 74 [556]: SELF      R1 R1 K13    ; R2 := R1; R1 := R1["write"]
 75 [556]: GETGLOBAL R3 K10       ; R3 := string
 76 [556]: GETTABLE  R3 R3 K11    ; R3 := R3["format"]
 77 [556]: LOADK     R4 K27       ; R4 := ", KEY2 = %d"
 78 [556]: GETGLOBAL R5 K18       ; R5 := key2
 79 [556]: CALL      R3 3 0       ; R3,... := R3(R4,R5)
 80 [556]: CALL      R1 0 1       ; R1(R2,...)
 81 [559]: GETGLOBAL R1 K0        ; R1 := saveFile
 82 [559]: SELF      R1 R1 K13    ; R2 := R1; R1 := R1["write"]
 83 [559]: LOADK     R3 K28       ; R3 := " },\n"
 84 [559]: CALL      R1 3 1       ; R1(R2,R3)
 85 [562]: GETGLOBAL R1 K15       ; R1 := idx
 86 [562]: ADD       R1 R1 K6     ; R1 := R1 + 1
 87 [562]: SETGLOBAL R1 K15       ; idx := R1
 88 [563]: GETGLOBAL R1 K21       ; R1 := GetUserHotKeyInfo
 89 [563]: GETGLOBAL R2 K5        ; R2 := tabNum
 90 [563]: GETGLOBAL R3 K15       ; R3 := idx
 91 [563]: CALL      R1 3 5       ; R1,R2,R3,R4 := R1(R2,R3)
 92 [563]: SETGLOBAL R4 K20       ; behaviorDes := R4
 93 [563]: SETGLOBAL R3 K19       ; keyDes := R3
 94 [563]: SETGLOBAL R2 K18       ; key2 := R2
 95 [563]: SETGLOBAL R1 K17       ; key1 := R1
 96 [547]: GETGLOBAL R1 K15       ; R1 := idx
 97 [547]: GETGLOBAL R2 K22       ; R2 := tableLen
 98 [547]: LT        1 R1 R2      ; if R1 < R2 then PC := 47
 99 [547]: JMP       47
100 [566]: GETGLOBAL R1 K0        ; R1 := saveFile
101 [566]: SELF      R1 R1 K13    ; R2 := R1; R1 := R1["write"]
102 [566]: LOADK     R3 K29       ; R3 := "}\n\n"
103 [566]: CALL      R1 3 1       ; R1(R2,R3)
104 [569]: GETGLOBAL R1 K5        ; R1 := tabNum
105 [569]: ADD       R1 R1 K6     ; R1 := R1 + 1
106 [569]: SETGLOBAL R1 K5        ; tabNum := R1
107 [536]: GETGLOBAL R1 K5        ; R1 := tabNum
108 [536]: LE        1 R1 K7      ; if R1 <= 3 then PC := 13
109 [536]: JMP       13
110 [572]: GETGLOBAL R1 K1        ; R1 := io
111 [572]: GETTABLE  R1 R1 K30    ; R1 := R1["close"]
112 [572]: GETGLOBAL R2 K0        ; R2 := saveFile
113 [572]: CALL      R1 2 1       ; R1(R2)
114 [573]: RETURN    R0 1         ; return 
